{"batchcomplete":true,"query":{"pages":[{"pageid":4734,"ns":0,"title":"4月4日","revisions":[{"slots":{"main":{"contentmodel":"wikitext","contentformat":"text/x-wiki","content":"{{カレンダー 4月}}\n'''4月4日'''（しがつよっか）は、[[グレゴリオ暦]]で年始から94日目（[[閏年]]では95日目）にあたり、年末まであと271日ある。誕生花は[[アジアンタム]]、[[トリテリア]]。\n\n== できごと ==\n<!-- [[Image:Sirfrancisdrake.jpg|thumb|170px|海賊[[フランシス・ドレーク]]、[[ナイト]]となる(1581)]] -->\n[[Image:Truman_signing_the_North_Atlantic_Treaty.gif|thumb|180px|[[北大西洋条約]]が締結され[[北大西洋条約機構|NATO]]発足(1949)]]\n[[Image:World Trade Center, New York City - aerial view (March 2001).jpg|thumb|upright|[[ワールドトレードセンター (ニューヨーク)|ワールドトレードセンター]]落成(1973)]]\n* [[1081年]] - [[アレクシオス1世コムネノス]]が[[東ローマ帝国]]皇帝に即位。[[コムネノス王朝]]が始まる。\n* [[1581年]] - [[海賊]][[フランシス・ドレーク]]が[[エリザベス1世|エリザベス女王]]から[[ナイト]]の爵位を受ける。\n* [[1660年]] - [[清教徒革命]]: オランダに亡命中の元スコットランド王[[チャールズ2世 (イングランド王)|チャールズ2世]]が{{仮リンク|ブレダ宣言|en|Declaration of Breda}}を発布。\n* [[1721年]] - [[ロバート・ウォルポール]]がイギリスの初代[[イギリスの首相|首相]]に就任。\n* [[1814年]] - フランス皇帝[[ナポレオン・ボナパルト]]が将軍連の反乱により退位させられる。\n* [[1840年]]（[[天保]]11年[[3月2日 (旧暦)|3月2日]]） - [[水野忠邦]]の抜擢により勘定奉行・[[遠山景元]]が[[町奉行|北町奉行]]に着任。\n* [[1841年]] - アメリカ大統領[[ウィリアム・ハリソン]]が就任1か月で死去。副大統領[[ジョン・タイラー]]が大統領に就任。\n* [[1873年]] - イギリスで世界最古の[[ケネルクラブ]]である[[ケネルクラブ|ザ・ケネルクラブ]]設立。\n* [[1875年]] - [[明治天皇]]に木村屋（現:[[木村屋總本店]]）の[[あんパン]]が献上される。\n* [[1879年]] - [[琉球藩]]の廃止と[[沖縄県]]設置を全国に布告。<!-- [[沖縄県]]の「3月」の記述は、3月27日に首里城で琉球藩主・尚泰に廃藩置県を通達した日 -->\n* [[1884年]] - [[ボリビア]]と[[チリ]]が[[太平洋戦争_(1879年-1884年)|太平洋戦争]]の休戦条約・[[バルパライソ条約]]を締結。\n* [[1890年]] - ラフカディオ・ハーン（[[小泉八雲]]）が来日。\n* [[1917年]] - 日本がロシアの臨時政府を承認\n* [[1924年]] - [[ダグラス DWC]]が、編成部隊による[[:en:First aerial circumnavigation|初の航空機世界一周]]へ出発する。175日をかけて、[[9月28日]]に達成。\n* [[1939年]] - [[イラク王国|イラク]]国王[[ガージー (イラク王)|ガージー]]が交通事故死。3歳の[[ファイサル2世 (イラク王)|ファイサル2世]]が即位。\n* [[1949年]] - ワシントンで西側12か国が[[北大西洋条約]]に調印。[[8月24日]]に[[北大西洋条約機構]] (NATO) が発足。\n* [[1954年]] - [[アルトゥーロ・トスカニーニ]]の最後の演奏会。（[[NBC交響楽団]]。オール・[[リヒャルト・ワーグナー|ワーグナー]]・プログラム）\n* [[1960年]] - [[セネガル]]が[[フランス]]から独立。\n* [[1964年]] - アメリカ[[ビルボード]]ヒットチャートの1位から5位までを[[ビートルズ]]が独占する。（1位「[[キャント・バイ・ミー・ラブ]]」、2位「[[ツイスト・アンド・シャウト]]」、3位「[[シー・ラヴズ・ユー]]」、4位「[[抱きしめたい]]」、5位「[[プリーズ・プリーズ・ミー (曲)|プリーズ・プリーズ・ミー]]」）\n* [[1968年]] - [[マーティン・ルーサー・キング]]（キング牧師）が暗殺される。\n* 1968年 - アメリカで無人宇宙船「[[アポロ6号]]」が打上げ。\n* [[1972年]] - [[沖縄返還協定|沖縄返還交渉]]の機密を漏洩した容疑で、毎日新聞社の[[西山太吉]]記者らを逮捕。（[[西山事件]]）\n* [[1973年]] - [[ニューヨーク]]の[[ワールドトレードセンター (ニューヨーク)|ワールドトレードセンター]]が正式にオープンされる。\n* 1973年 - [[日本]]の[[最高裁判所 (日本)|最高裁判所]]が[[尊属殺]]の重罰規定は[[違憲判決|違憲]]と判決（[[尊属殺重罰規定違憲判決]]）。日本の最高裁にとって初めて[[違憲審査制|違憲立法審査権]]の行使。\n* [[1975年]] - [[ビル・ゲイツ]]と[[ポール・アレン]]が[[ニューメキシコ州]][[アルバカーキ]]に[[マイクロソフト|Microsoft]]を設立。\n* 1975年 - [[ベトナム戦争]]: アメリカ軍が[[南ベトナム]]の孤児をアメリカ合衆国本土などに避難させる作戦・[[オペレーション・ベビーリフト]]を開始。第1便の飛行機が墜落し153人が死亡。\n* [[1978年]] - [[キャンディーズ]]が解散。後楽園に55,000人を動員し、4時間にわたるコンサートを開催。\n* [[1979年]] - [[パキスタン]]前首相[[ズルフィカール・アリー・ブットー]]が処刑される。\n* [[1982年]] - お笑いコンビ、[[ダウンタウン (お笑いコンビ)|ダウンタウン]]結成。\n* [[1983年]] - [[スペースシャトル]]「[[チャレンジャー (オービタ)|チャレンジャー]]」が[[STS-6]]で初飛行。\n* 1983年 - NHK[[連続テレビ小説]]『[[おしん]]』が放送開始。\n* [[1994年]] - [[ジム・クラーク (事業家)|ジム・クラーク]]と[[マーク・アンドリーセン]]がモザイク・コミュニケーションズ（後の[[ネットスケープコミュニケーションズ]]）を設立。\n* [[1997年]] - [[オレンジ共済組合事件]]で起訴された[[友部達夫]]議員の[[議員辞職勧告決議]]が可決。\n* [[1998年]] - プロレスラー[[アントニオ猪木]]引退。\n* [[1999年]] - [[第71回選抜高等学校野球大会]]で、[[沖縄尚学高等学校]]が沖縄県勢として初優勝。\n* [[2016年]] - 日本、[[バスタ新宿]]が開業<ref>{{Cite web |date=2016-04-05 |url=http://www.sankei.com/life/news/160405/lif1604050014-n1.html |title=乗り換え「楽になる」 発着1日最大1600便超 バスタ新宿 |work=産経ニュース |publisher=産業経済新聞社 |accessdate=2018-04-11}}</ref>。\n\n== 誕生日 ==\n=== 人物 ===\n<!-- [[Image:Pierre-Paul_Prud%27hon_003.jpg|thumb|160px|[[ロマン主義]]の画家[[ピエール＝ポール・プリュードン]](1758-1823)誕生。像は『プシュケの略奪』(1800)]] -->\n[[Image:Edward_Hicks_-_Peaceable_Kingdom.jpg|thumb|240px|[[フォークアート]]の画家[[エドワード・ヒックス]](1780-1849)誕生。画像は『平和な王国』(1834頃)]]\n[[Image:Lautr%C3%A9amont.jpg|thumb|upright|詩人[[ロートレアモン伯爵]](1846-1870)。<!--『{{仮リンク|マルドロールの歌|fr|Les Chants de Maldoror}}』は[[シュルレアリスム|シュルレアリスト]]らに大きな影響を与えた。-->{{Squote|<!--彼は美しい、（中略）そしてとりわけ、-->解剖台の上でのミシンと蝙蝠傘の偶然の出逢いのように美しい！（『マルドロールの歌』[[wikisource:fr:Les Chants de Maldoror/Chant VI|第6歌]]）}}]]\n[[Image:Shimei_Futabatei.jpg|thumb|upright|日本近代小説の先駆者、[[二葉亭四迷]](1864-1909)]]\n[[Image:Isoroku_Yamamoto.jpg|thumb|upright|[[第二次世界大戦]]初期の[[連合艦隊司令長官]]、[[山本五十六]](1884-1943)]]\n<!--[[Image:Tarkovsky_vgik.jpg|thumb|170px|[[映画監督]][[アンドレイ・タルコフスキー]](1932-1986)]]-->\n* [[186年]] - [[カラカラ]]、[[ローマ皇帝]]（+ [[217年]]）\n* [[1415年]]（[[応永]]22年[[2月25日 (旧暦)|2月25日]]） - [[蓮如]]、[[室町時代]]の[[僧]]（+ [[1499年]]）\n* [[1640年]] - [[ガスパル・サンス]]、[[作曲家]]（+ [[1710年]]）\n* [[1648年]] - [[グリンリング・ギボンズ]]、[[彫刻家]]（+ [[1721年]]）\n* [[1688年]] - [[ジョゼフ＝ニコラ・ドリル]]、[[天文学者]]（+ [[1768年]]）\n* [[1758年]] - [[ピエール＝ポール・プリュードン]]、[[画家]]（+ [[1823年]]）\n* [[1780年]] - [[エドワード・ヒックス]]、画家（+ [[1849年]]）\n* [[1785年]] - [[ベッティーナ・フォン・アルニム]]、[[作家]]（+ [[1859年]]）\n* [[1800年]]（[[寛政]]12年[[3月11日 (旧暦)|3月11日]]） - [[徳川斉昭]]、第9代[[水戸藩|水戸藩主]]、[[徳川慶喜]]の父（+ [[1860年]]）\n* [[1809年]] - [[ベンジャミン・パース (数学者)|ベンジャミン・パース]]、[[数学者]]（+ [[1880年]]）\n* [[1819年]] - [[マリア2世 (ポルトガル女王)|マリア2世]]、[[ポルトガル王国|ポルトガル]][[女王]]（+ [[1853年]]）\n* [[1826年]] - [[ゼノブ・グラム]]、[[電気]]技術者（+ [[1901年]]）\n* [[1829年]]（[[文政]]12年[[3月1日 (旧暦)|3月1日]]） - [[井上源三郎]]、[[新選組]]六番隊組長（+ [[1868年]]）\n* [[1842年]] - [[エドゥアール・リュカ]]、数学者（+ [[1891年]]）\n* [[1843年]] - [[ハンス・リヒター (指揮者)|ハンス・リヒター]]、[[指揮者]]（+ [[1916年]]）\n* [[1846年]] - [[ロートレアモン伯爵]]、[[詩人]]、[[作家]]（+ [[1870年]]）\n* [[1851年]]（[[嘉永]]4年[[3月3日 (旧暦)|3月3日]]） - [[荻野吟子]]、近代[[日本]]最初の女性[[医師]]（+ [[1913年]]）\n* [[1852年]] - [[アーサー・コールマン]]、[[地質学|地質学者]]（+ [[1939年]]）\n* [[1853年]] - [[タッド・リンカーン]]、第16代[[アメリカ合衆国大統領]][[エイブラハム・リンカーン]]の四男（+ [[1871年]]）\n* [[1862年]] - [[レオニード・パステルナーク]]、[[画家]]（+ [[1945年]]）\n* [[1864年]]（[[元治]]元年[[2月28日 (旧暦)|2月28日]]） - [[二葉亭四迷]]、[[小説家]]（+ [[1909年]]）\n* [[1875年]] - [[ピエール・モントゥー]]、指揮者（+ [[1964年]]）\n* [[1876年]] - [[モーリス・ド・ヴラマンク]]、画家（+ [[1958年]]）\n* [[1877年]] - [[古今亭志ん生 (4代目)|古今亭志ん生]]（四代目）、[[落語家]]（+ [[1926年]]）\n* [[1879年]] - [[アイモ・カヤンデル]]、[[フィンランドの首相一覧|フィンランド首相]]（+ [[1943年]]）\n* [[1880年]] - [[ゲオルク・フォン・トラップ]]、[[軍人]]（+ [[1947年]]）\n* [[1882年]] - [[エミール・フィラ]]、[[画家]]、彫刻家（+ [[1953年]]）\n* 1882年 - [[クルト・フォン・シュライヒャー]]、軍人、[[政治家]]（+ [[1934年]]）\n* [[1884年]] - [[山本五十六]]、[[連合艦隊司令長官]]（+ [[1943年]]）\n* [[1885年]] - [[中里介山]]、作家（+ [[1944年]]）\n* 1885年 - [[本居長世]]、[[童謡]]作曲家（+ [[1945年]]）\n* [[1888年]] - [[トリス・スピーカー]]、[[メジャーリーグベースボールの選手一覧|メジャーリーガー]]（+ [[1958年]]）\n* [[1894年]] - [[瀧井孝作]]、[[小説家]]、[[俳人]]（+ [[1984年]]）\n* [[1900年]] - [[市村清]]、[[実業家]]（+ [[1968年]]）\n* [[1914年]] - [[マルグリット・デュラス]]、[[作家]]、[[映画監督]]（+ [[1996年]]）\n* [[1915年]] - [[江口行男]]、元[[プロ野球選手]]（+ 没年不明）\n* 1915年 - [[マディ・ウォーターズ]]、[[ブルース]][[歌手|シンガー]]、[[ギタリスト]]（+ [[1983年]]）\n* [[1918年]] - [[塩月弥栄子]]、[[茶道家]]（+ [[2015年]]） \n* [[1919年]] - [[原信太郎]]、[[鉄道模型]]収集家（+ [[2014年]]）\n* [[1920年]] - [[エリック・ロメール]]、[[映画監督]]（+ [[2010年]]）\n* [[1922年]] - [[エルマー・バーンスタイン]]、[[作曲家]]（+ [[2004年]]）\n* [[1924年]] - [[ギル・ホッジス]]、元[[メジャーリーガー]]（+ [[1972年]]）\n* [[1925年]] - [[デットマール・クラマー]]、[[サッカー選手]]、指導者（+ [[2015年]]）\n* [[1926年]] - [[リシャルト・バクスト]]、[[ピアニスト]]（+ [[1999年]]）\n* [[1927年]] - [[宮本陽吉]]、[[アメリカ文学|アメリカ文学者]]（+ [[1996年]]）\n* 1927年 - [[若城希伊子]]、小説家、[[脚本家]]（+ [[1998年]]）\n* [[1929年]] - [[照屋林助]]、歌謡漫談家（+ [[2005年]]）\n* [[1932年]] - [[アンドレイ・タルコフスキー]]、[[映画監督]]（+ [[1986年]]）\n* 1932年 - [[アンソニー・パーキンス]]、[[俳優]]（+ [[1992年]]）\n* 1932年 - [[後藤明生]]、小説家（+ [[1999年]]）\n* 1932年 - [[長谷部安春]]、映画監督（+ [[2009年]]）\n* [[1936年]] - [[鈴木徹 (野球)|鈴木徹]]、元プロ野球選手（+ [[2004年]]）\n* [[1938年]] - [[細木数子]]、[[宗教家]]、[[占い|占い師]]\n* 1938年 - [[A・バートレット・ジアマッティ]]、MLB[[コミッショナー]]（+ [[1989年]]）\n* [[1942年]] - [[ジム・フレゴシ]]、元メジャーリーガー\n* [[1945年]] - [[山本拓 (経済学者)|山本拓]]、経済学者\n* 1945年 - [[小嶋光信]]、[[両備グループ]]代表\n* 1945年 - [[菅原勝矢]]、元プロ野球選手\n* [[1946年]] - [[佐藤勝昭]]、[[空手道|空手家]]\n* [[1947年]] - [[あき竹城]]、[[俳優|女優]]\n* 1947年 - [[サルヴァトーレ・シャリーノ]]、作曲家\n* [[1948年]] - [[のこいのこ]]、[[歌手]]\n* 1948年 - [[ダン・シモンズ]]、作家\n* [[1949年]] - [[シン・トゥン・ヤウ]]、[[数学者]]\n* [[1950年]] - [[斉藤哲夫]]、[[シンガーソングライター]]\n* [[1951年]] - [[佐野実]]、実業家、支那そばや創業者（+ [[2014年]]）\n* 1951年 - [[フン・セン]]、[[カンボジアの首相|カンボジア首相]]\n* [[1952年]] - [[大橋俊夫]]、[[ラジオ]][[アナウンサー]]\n* 1952年 - [[ゲイリー・ムーア]]、[[ミュージシャン]]（+ [[2011年]]）\n* 1952年 - [[カレン・マグヌセン]]、[[フィギュアスケート]]選手\n* 1952年 - [[ローズマリー・アッカーマン]]、[[陸上競技選手一覧|陸上競技選手]]\n* [[1953年]] - [[小山田春樹]]、アナウンサー、[[エッセイスト]]\n* [[1954年]] - [[ミシェル・カミロ]]、[[ジャズ]][[ピアニスト]]\n* [[1955年]] - [[高橋俊春]]、元プロ野球選手\n* [[1956年]] - [[松田弘]]、[[ミュージシャン]]（[[サザンオールスターズ]]）\n* 1956年 - [[中村典夫]]、元プロ野球選手\n* 1956年 - [[百崎敏克]]、高校野球指導者\n* 1956年 - [[トム・ハー]]、メジャーリーガー\n* [[1957年]] - [[板垣恵介]]、[[漫画家]]\n* 1957年 - [[桑野信義]]、[[タレント]]、ミュージシャン（元[[ラッツ&スター]]）\n* 1957年 - [[ウォルター・ヴァン・ベイレンドンク]]、[[ファッションデザイナー]]\n* 1957年 - [[アキ・カウリスマキ]]、映画監督\n* [[1958年]] - [[山本昌邦]]、[[サッカー選手一覧|サッカー選手]]、監督\n* 1958年 - [[斎藤貴男]]、[[ジャーナリスト]]\n* [[1960年]] - [[深浦加奈子]]、女優（+ [[2008年]]）\n* 1960年 - [[ヒューゴ・ウィーヴィング]]、俳優\n* [[1961年]] - [[松井菜桜子]]、[[声優]]\n* [[1962年]] - [[レイ・マーサー]]、[[プロボクサー]]\n* [[1963年]] - [[萩原一至]]、漫画家\n* 1963年 - [[斉木かおり]]、アナウンサー\n* [[1964年]] - [[小沢章一]]、高校野球指導者（+ [[2006年]]）\n* 1964年 - [[上地和彦]]、プロ野球選手\n* [[1965年]] - [[エレイン・ザヤック]]、[[フィギュアスケート]]選手\n* 1965年 - [[ロバート・ダウニー・Jr]]、俳優\n* [[1966年]] - [[橋本由香利]]、ミュージシャン、作曲家、編曲家\n* 1968年 - [[岩崎久則]]、元プロ野球選手\n* [[1969年]] - [[ピョートル・アンデルジェフスキ]]、[[ピアニスト]]\n* [[1970年]] - [[エレーナ・エレシナ]]、走り高跳び選手\n* [[1971年]] - [[大渡亮]]、ミュージシャン（[[Do As Infinity]]ギタリスト）\n* 1971年 - [[芝崎和広]]、元プロ野球選手\n* [[1972年]] - [[ジル・スコット]]、シンガーソングライター\n* [[1973年]] - [[デビッド・ブレイン]]、[[マジシャン (奇術)|奇術師]]\n* [[1974年]] - [[ワシリー・ジロフ]]、プロボクサー\n* 1974年 - [[照英]]、[[俳優]]\n<!-- 特筆性は? * 1974年 - [[松下敏宏]]、[[お笑いタレント]]（元[[バカリズム]]） -->\n* 1974年 - [[野上修]]、[[野球選手]]\n* [[1975年]] - [[河合彩]]、元[[フィギュアスケート]]選手、[[アナウンサー]]\n* 1975年 - [[スコット・ローレン]]、メジャーリーガー\n* [[1976年]] - [[エメルソン・フェレイラ・ダ・ローザ]]、[[サッカー選手一覧|サッカー選手]]\n* [[1977年]] - [[エリック・バレント]]、元プロ野球選手\n* 1977年 - [[原田曜平]]、マーケティングアナリスト\n* [[1978年]] - [[アベユウキ]]、[[ファッションモデル]]\n* 1979年 - [[吉田大吾]]、[[お笑い芸人]]（[[POISON GIRL BAND]]）\n* 1979年 - [[ヒース・レジャー]]、俳優（+ [[2008年]]）\n* 1979年 - [[ナターシャ・リオン]]、女優\n* 1979年 - [[チャールズ・バトラー (フィギュアスケート選手)|チャールズ・バトラー]]、[[フィギュアスケート]]選手\n* [[1980年]] - [[ビヨン・ビルドハイム]]、[[自動車競技|レーシングドライバー]]\n* [[1981年]] - [[夏達]]、[[漫画家]]\n* 1981年 - [[小瀋陽]]、[[コメディアン]]\n* 1981年 - [[フェデリコ・バエス]]、野球選手\n* [[1983年]] - [[有田気恵]]、タレント\n* 1983年 - [[ベン・ゴードン]]、[[バスケットボール選手一覧|バスケットボール選手]]\n* [[1984年]] - [[溝口大樹]]、元プロ野球選手\n* 1984年 - [[星野真澄]]、プロ野球選手\n<!-- 特筆性は? * [[1985年]] - 桑原彰、ミュージシャン（[[RADWIMPS]]） -->\n* [[1985年]] - [[ルディ・フェルナンデス (バスケットボール)|ルディ・フェルナンデス]]、バスケットボール選手\n* 1985年 - [[松本晃]]、[[野球選手]]\n* [[1986年]] - [[岩崎恭平]]、プロ野球選手\n* 1986年 - [[中ノ森文子]]、ミュージシャン（[[中ノ森BAND]]）\n* 1986年 - [[かっすん]]、元お笑いタレント（[[チェリー☆パイ]]）\n* 1986年 - [[加藤ゆり]]、タレント\n* 1986年 - [[アンソニー・カーター (野球)|アンソニー・カーター]]、プロ野球選手\n* [[1988年]] - [[ザイド・ヘンドリックス]]、野球選手\n* 1988年 - [[野原将志]]、プロ野球選手\n* [[1989年]] - [[久保賢司]]、[[キックボクサー]]\n* 1989年 - [[マッシミリアーノ・タッリャーニ]]、サッカー選手\n* 1989年 - [[村上東奈]]、女優、タレント\n* [[1990年]] - [[三原勇希]]、モデル\n* 1990年 - [[齋藤学]]、サッカー選手\n* [[1991年]] - [[森崎アリス]]、モデル、タレント\n* [[1991年]] - [[金子織江]]、グラビアアイドル\n* 1991年 - [[小池唯]]、グラビアアイドル\n* 1991年 - [[マーティン・ペレス]]、メジャーリーガー\n* [[1993年]] - [[フランク・カミンスキー]]、バスケットボール選手\n* [[1994年]] - [[菅谷梨沙子]]、歌手、[[Berryz工房]]メンバー\n* 1994年 - [[黒田瑞貴]]、[[ファッションモデル]]、[[タレント]]、[[俳優|女優]]\n* 1994年 - [[西川俊介]]、俳優\n* 1994年 - [[北本亘]]、プロ野球選手\n<!-- 個人としての特筆性は? * 1994年 - カンタ、YouTuber（[[水溜りボンド]]） -->\n* [[1996年]] - [[桃瀬なつみ]]、グラビアアイドル\n* 1996年 - [[オースティン・マホーン]]、歌手\n<!-- 特筆性は? * 1996年 - 岡本尚子、アイドル（[[HKT48]]） -->\n* 1996年 - [[土屋神葉]]、俳優・声優、女優・[[土屋太鳳]]の弟\n<!-- 特筆性は? * 1999年 - 西野未姫、アイドル（[[AKB48]]） -->\n<!-- 特筆性は? * 2002年 - 岡田愛、アイドル ([[さくら学院]]) -->\n* 生年不詳 - [[松本洋子]]、漫画家\n* 生年不明 - [[片貝薫]]、声優\n\n=== 人物以外（動物など） ===\n* [[1957年]] - [[ケルソ]]、[[競走馬]]（+ [[1983年]]）\n* [[1987年]] - [[メルシーアトラ]]、競走馬（+ [[1991年]]）\n* [[1991年]] - [[ボディーガード (競走馬)|ボディーガード]]、競走馬（+ 不明）\n* [[1993年]] - [[エイシンサンディ]]、競走馬\n* 1993年 - [[トーヨーシアトル]]、競走馬\n* [[1995年]] - [[エアスマップ]]、競走馬\n* [[1995年]] - [[ファレノプシス (競走馬)|ファレノプシス]]、競走馬\n* [[1996年]] - [[ナリタトップロード]]、競走馬（+ [[2005年]]）\n* 1996年 - [[レッドチリペッパー]]、競走馬\n* [[2003年]] - [[ウェルアームド]]、競走馬\n* [[2004年]] - [[ウオッカ]]、競走馬\n\n== 忌日 ==\n[[Image:Sant%27Ambrogio_Cript_in_Basilica_of_Sant%27Ambrogio%2C_Milan.jpg|thumb|140px|[[ミラノ]][[司教]][[アンブロジウス]](?-397)没。四大[[教会博士]]の1人とされる]]\n[[Image:Isidoro_de_Sevilla_%28Jos%C3%A9_Alcoverro%29_01.jpg|thumb|upright|四大[[教会博士]]のもう1人、知識の集積に優れた[[神学者]][[イシドールス]](560-636)没。[[プログラマ]]の[[守護聖人]]である]]\n[[Image:John_Napier.jpg|thumb|upright|[[数学者]][[ジョン・ネイピア]](1550-1617)。[[対数]]を考案した]]\n<!-- [[Image:Crookes_William.jpg|thumb|upright|[[化学者]]・[[物理学者]]、[[ウィリアム・クルックス]](1832-1919)。[[タリウム]]を発見]] -->\n[[Image:Martin-Luther-King-1964-leaning-on-a-lectern.jpg|thumb|170px|[[アフリカ系アメリカ人]][[公民権運動]][[マーティン・ルーサー・キング]](1929-1968)、凶弾に斃れる。{{Squote|今夜、私は幸せです。私には何の心配もない。私は誰も恐れない。私の目は主の再臨の栄光を見たのです。――暗殺直前の演説}}]]\n<!-- [[Image:Case Study House No. 22.JPG|thumb|180px|[[建築家]][[ピエール・コーニッグ]]。画像はケーススタディハウスNo.22(1960)]] -->\n* [[397年]] - [[アンブロジウス]]、キリスト教の[[ラテン教父]]、[[ミラノ]][[司教]]（* [[340年]]頃）\n* [[636年]] - [[イシドールス]]、[[神学者]]（* [[560年]]）\n* [[896年]] - [[フォルモスス (ローマ教皇)|フォルモスス]]、第111代[[教皇|ローマ教皇]]\n* [[1284年]] - [[アルフォンソ10世 (カスティーリャ王)|アルフォンソ10世]]、[[カスティーリャ王国|カスティーリャ王]]（* [[1221年]]）\n* [[1292年]] - [[ニコラウス4世 (ローマ教皇)|ニコラウス4世]]、第191代ローマ教皇（* [[1227年]]）\n* [[1305年]] - [[フアナ1世 (ナバラ女王)|フアナ1世]]、[[ナバラ王国|ナバラ女王]]、[[シャンパーニュ伯|シャンパーニュ女伯]]（* [[1271年]]頃）\n* [[1536年]] - [[フリードリヒ2世 (ブランデンブルク＝アンスバッハ辺境伯)|フリードリヒ5世]]、[[アンスバッハ侯領|ブランデンブルク＝アンスバッハ辺境伯]]（* [[1460年]]）\n* [[1566年]] - [[ダニエレ・ダ・ヴォルテッラ]]、[[画家]]、[[彫刻家]]（* [[1509年]]頃）\n* [[1588年]] - [[フレゼリク2世 (デンマーク王)|フレゼリク2世]]、[[デンマーク|デンマーク王]]（* [[1534年]]）\n* [[1617年]] - [[ジョン・ネイピア]]、[[数学者]]（* [[1550年]]）\n* [[1643年]] - [[シモン・エピスコピウス]] ([[:en:Simon Episcopius|Simon Episcopius]])、神学者（* [[1583年]]）\n* [[1773年]]（[[安永 (元号)|安永]]2年[[3月13日 (旧暦)|3月13日]]） - [[瀬川菊之丞 (2代目)]]、[[歌舞伎]]役者（* [[1741年]]）\n* [[1807年]] - [[ジェローム・ラランド]]、[[天文学者]]（* [[1732年]]）\n* [[1817年]] - [[アンドレ・マッセナ]]、[[フランス第一帝政]]時代の[[元帥]]（* [[1758年]]）\n* [[1841年]] - [[ウィリアム・ハリソン|ウィリアム・H・ハリスン]]、第9代[[アメリカ合衆国大統領]]（* [[1773年]]）\n* [[1861年]] - [[ジョン・マクレーン (郵政長官)|ジョン・マクレーン]]、第9代[[アメリカ合衆国郵政長官]]（* [[1785年]]）\n* [[1889年]] - [[ギーゼラ・フォン・アルニム]]、[[作家]]（* [[1827年]]）\n* [[1919年]] - [[ウィリアム・クルックス]]、[[化学者]]、[[物理学者]]（* [[1832年]]）\n* [[1923年]] - [[ユーリー・マルトフ]]、[[ロシア]]の[[社会主義]]運動家（* [[1873年]]）\n* 1923年 - [[ジョン・ベン]]、[[数学者]]（* [[1834年]]）\n* [[1929年]] - [[カール・ベンツ]]、[[ガソリン]][[自動車]]を開発した技術者、[[ダイムラー (自動車メーカー)|ダイムラー]]の創業者のひとり（* [[1844年]]）\n* [[1931年]] - [[アンドレ・ミシュラン]] ([[:en:André Michelin|André Michelin]])、[[ミシュラン]]社の創業者（* [[1853年]]）\n* [[1932年]] - [[ヴィルヘルム・オストヴァルト]]、化学者（* [[1853年]]）\n* 1932年 - [[岡田信一郎]]、[[建築家]]（* [[1883年]]）\n* [[1939年]] - [[ガージー (イラク王)|ガージー]]、[[イラク王国|イラク王]]（* [[1912年]]）\n* [[1944年]] - [[アルマ・ロゼ]]、[[ヴァイオリニスト]]（* [[1906年]]）\n* [[1947年]] - [[ジェイムズ・ガスコイン＝セシル (第4代ソールズベリー侯爵)]]、イギリスの政治家、貴族（* [[1861年]]）\n* [[1953年]] - [[カロル2世 (ルーマニア王)|カロル2世]]、[[ルーマニア王国|ルーマニア王]]（* [[1893年]]）\n* [[1954年]] - [[三門順子]]、[[歌手]]（* [[1915年]]）\n* [[1957年]] - [[エドガートン・ハーバート・ノーマン]]、[[外交官]]、[[日本学|日本学者]]（* [[1909年]]）\n* [[1962年]] - [[ハンラッティ事件|ジェームズ・ハンラッティ]]、ハンラッティ事件の被告（* [[1936年]]）\n* [[1968年]] - [[マーティン・ルーサー・キング]]、牧師、黒人運動指導者（* [[1929年]]）\n* [[1971年]] - [[カール・メイズ]]、メジャーリーガー（* [[1891年]]）\n* [[1972年]] - [[シュテファン・ヴォルペ]]、[[作曲家]]（* [[1902年]]）\n* [[1973年]] - [[菊田一夫]]、[[劇作家]]（* [[1908年]]）\n* [[1976年]] - [[ハリー・ナイキスト]]、物理学者（* [[1889年]]）\n* [[1977年]] - [[亘四郎]]、[[政治家]]（* [[1899年]]）\n* [[1979年]] - [[ズルフィカール・アリー・ブットー]]、[[パキスタンの大統領|パキスタン大統領]]・[[パキスタンの首相|首相]]（* [[1928年]]）\n* [[1981年]] - [[カール・ジーゲル]]、[[数学者]]（* [[1896年]]）\n* [[1983年]] - [[グロリア・スワンソン]]、[[俳優|女優]]（* [[1899年]]）\n* [[1984年]] - [[オリェーク・アントーノフ]]、[[航空機]]技術者（* [[1906年]]）\n* [[1987年]] - [[C・L・ムーア]]、[[SF作家]]（* [[1911年]]）\n* [[1991年]] - [[フォレスト・タウンズ]]、[[陸上競技]]選手（* [[1914年]]）\n* 1991年 - [[マックス・フリッシュ]]、[[作家]]、[[建築家]]（* [[1911年]]）\n* [[1992年]] - [[サミュエル・ハーマン・レシェフスキー]]、[[チェス]]の選手（* [[1911年]]）\n* [[1994年]] - [[平野三郎]]、政治家（* [[1912年]]）\n* [[1995年]] - [[山下実]]、[[プロ野球選手]]・[[プロ野球監督|監督]]・[[プロ野球審判員|審判]]（* [[1907年]]）\n* [[1996年]] - [[野副鉄男]]、化学者（* [[1902年]]）\n* 1996年 - [[バーニー・ユーウェル]]、陸上競技選手（* [[1918年]]）\n* [[1997年]] - [[杉村春子]]、女優（* [[1906年]]）\n* [[1999年]] - [[アーリー・ウィン]]、[[メジャーリーグベースボール]]選手（* [[1920年]]）\n* [[2002年]] - [[秋元秀雄]]、政治[[評論家]]（* [[1926年]]）\n* [[2003年]] - [[光延旺洋]]、化学者（* [[1934年]]）\n* [[2004年]] - [[ピエール・コーニッグ]]、[[建築家]]（* [[1925年]]）\n* [[2006年]] - [[原田慎太郎 (政治家)|原田慎太郎]]、[[宗像市]][[市町村長|長]]（* [[1941年]]）\n* 2006年 - [[エックハルト・ダッゲ]]、[[プロボクサー]]（* [[1948年]]）\n* [[2008年]] - [[呉学謙]]、[[中華人民共和国外交部|中華人民共和国外交部長]]・副総理（* [[1921年]]）\n* 2008年 - [[成瀬正俊]]、[[俳人]]（* [[1930年]]）\n* [[2010年]] - [[奥山かずお]]、[[児童文学]]作家（* [[1939年]]）\n* [[2011年]] - [[須賀良]]、俳優（* [[1936年]]）\n* [[2013年]] - [[ヤマグチノボル]]、[[ライトノベル]]作家（* [[1972年]]）\n\n== 記念日・年中行事 ==\n[[Image:Vietnam-landmine-victim.jpg|thumb|140px|[[地雷]]に関する啓発および地雷除去支援のための[[国際デー]]。画像は[[ベトナム]]の対人地雷被害者]]\n[[Image:Bean-jam-bun,anpan,katori-city,japan.JPG|thumb|240px|[[あんパン]]の日。[[1875年]]（明治8年）に[[明治天皇]]にあんパンが献上されたという]]\n\n* [[清明]]（{{JPN}} 2012年）\n*: [[二十四節気]]の1つ。[[太陽]]の黄経が15度の時で、万物がすがすがしく明るく美しいころ。\n\n* {{仮リンク|寒食節|zh|寒食節}}（{{CHN}}・{{KOR}} 2010年・2011年・2013年）\n*: [[清明]]の前日。この日は家で火を炊くことを忌み、冷たい物を食べる習慣があった。\n\n* 地雷に関する啓発および地雷除去支援のための国際デー（{{World}}）\n*: 国連が2006年に制定した[[国際デー]]。\n* [[ピアノ調律]]の日（{{World}}）\n*: [[国際ピアノ製造技師調律師協会]](IAPBT)が1993年に制定。4月の英語Aprilの頭文字が調律に使う音の名前[[イ (音名)|A]]と同じであり、その[[周波数]]が[[A440|440Hz]]であることから。<ref>[https://web.archive.org/web/20080705175801/http://www.jpta.org/2008/44-2008.html 「4月4日はピアノ調律の日」全国統一記念事業]（2008年7月5日時点の[[インターネットアーカイブ|アーカイブ]]） [[日本ピアノ調律師協会]]</ref>\n\n* [[子供の日|児童節]]（{{ROC}}・{{HKG}}）\n*: [[中華民国]]が[[1931年]]に制定。また、香港でも1931年から中華民国にあわせて4月4日を児童節としている。\n* [[独立記念日]]（{{SEN}}）\n*: [[1960年]]のこの日、セネガルが[[フランス]]から独立した。\n\n* 交通反戦デー（{{JPN}}）\n*: [[1989年]]のこの日に開かれた東京都の交通遺児を励ます会の「交通反戦大会」で制定。春休み期間中の覚えやすい日で、また「死(4)死(4)を返上」の語呂合せから。\n* [[あんパン]]の日（{{JPN}}）\n*: [[1875年]]4月4日、[[明治天皇]]が水戸邸の下屋敷を訪れる際に、[[木村屋總本店|木村屋]]のあんぱんが出されたことから。\n* [[ヨーヨー]]の日（{{JPN}}）\n*:「ハイパーヨーヨー」の販売元であった玩具メーカーの[[バンダイ]]が制定。\n* [[トランスジェンダー]]の日（{{JPN}}）\n*: [[1999年]][[2月]]に[[性同一性障害]]者の団体「TSとTGを支える人々の会」が制定。2013年に削除\n* [[幸せ]]の日（{{JPN}}）\n*: 女の子の節句（ひなまつり）が3月3日、男の子の節句（こどもの日）が5月5日、その間の今日が4月4日が『4（し）と4（し）』の合わさる日として『幸せの日』と云われている。また、男子（だんし）と女子（じょし）が歩み寄った日とも云われ、『男子と女子の夫々の「子（し）」』が合わさる日『幸せの日』と云われる事もある。\n* [[どらやき]]の日（{{JPN}}）\n*: [[上巳|桃の節句]]と[[端午|端午の節句]]に「はさまれた」日であることから。\n* [[養子]]の日（{{JPN}}）\n*: 4と4でようしの日である事から。[[2014年]]、[[特別養子縁組]]の認知度が低いことを問題視した[[日本財団]]が制定。\n* [[フォー]]の日（{{JPN}}）\n*: [[エースコック]]が制定<ref>{{Cite web |date=2016-04-03 |url=http://www.sankei.com/region/news/160403/rgn1604030056-n1.html |title=4月4日「フォーの日」に 大阪・吹田で登録証授与式 |publisher=産経ニュース |accessdate=2017-04-03}}</ref>。\n* [[四輪駆動]]の日（{{JPN}}）四輪駆動は、4×4（フォーバイフォー）ともいうことから、メルセデスベンツ日本が4月4日を四輪駆動の日として申請し。2016年から制定された。\n\n== フィクションのできごと ==\nGGO   ガンゲイルオンラインで第2回スクワットジャムが開催される\n『[[ソードアート・オンライン オルタナティブ ガンゲイル・オンライン]]』\n\n{{フィクションの出典明記|section=1|ソートキー=日0404|date=2011年8月3日 (水) 18:23 (UTC)}}\n\n=== 誕生日（フィクション） ===\n* [[1966年]] - 出目川仁、漫画・アニメ『[[DEATH NOTE]]』に登場するキャラクター<ref>{{Cite book |和書 |author = [[大場つぐみ]] |coauthors = [[小畑健]] |year = 2006 |title = DEATH NOTE |volume = 第13巻 |page = 34 |publisher = [[集英社]] |series = [[ジャンプ・コミックス]] |isbn = 978-4-08-874095-9 }}</ref>\n* [[1967年]] - 月光聖市、小説・漫画・アニメ『[[りゅうおうのおしごと!]]』に登場するキャラクター<ref>{{Cite book|和書|title=[[りゅうおうのおしごと!]]|volume=2|author=[[白鳥士郎]]|publisher=[[SBクリエイティブ]]|page=2|isbn=978-4-7973-8676-9}}</ref>\n* [[2014年]] - 天沢勇子、アニメ・小説『[[電脳コイル]]』に登場するキャラクター<ref>{{Cite book |和書 |year = 2006 |title = ロマンアルバム 電脳コイル |page = 15 |publisher = [[徳間書店]] |isbn = 978-4-08-874095-9 }}</ref>\n* 宇宙暦767年/帝国暦458年 - [[ヤン・ウェンリー]]、小説・アニメ『[[銀河英雄伝説]]』の登場人物{{要出典|date=2018年3月29日 (木) 15:29 (UTC)}}<ref>{{Cite news|title=「銀河英雄伝説」作者、ヤン・ウェンリーの誕生日は適当に決定と告白|date=2018-5-20|url=http://otakei.otakuma.net/archives/2012040605.html|accessdate=2018-05-20|publication-date=|work=おたくま経済新聞}}</ref>\n* 生年不明 - [[アイドルマスター SideM#紅井朱雀|紅井朱雀]]、ゲーム『[[アイドルマスター SideM]]』に登場するキャラクター<ref>ゲーム内のプロフィールより。</ref>\n* 生年不明 - 桜ノ宮苺香、漫画・アニメ『[[ブレンド・S]]』の主人公<ref>{{Cite book |和書 |author = [[中山幸]] |year = 2017 |title = ブレンド・S |volume = 3巻 |page = 6 |publisher = [[芳文社]] |series = [[まんがタイムKRコミックス]] |isbn = 978-4-8322-4798-7 }}</ref>\n* 生年不明 - 四天王うづき、[[読者参加型ゲーム|読者参加企画]]『[[HAPPY★LESSON]]』に登場するキャラクター<ref>{{Cite web |url=http://archive.asciimw.jp/mediamix/happy/chara/ |title=キャラクター紹介 |work=アーカイブ HAPPY★LESSON |publisher=アスキー・メディアワークス |accessdate=2012-02-14 |deadlinkdate=2014-06-17 |archiveurl=https://archive.is/20120726091502/http://archive.asciimw.jp/mediamix/happy/chara/ |archivedate=2012-07-26}}</ref>\n* 生年不明 - [[しまじろうシリーズの登場キャラクター#縞野家|縞野はな（はなちゃん）]]、ベネッセの教材『こどもちゃれんじ』、アニメ『[[しましまとらのしまじろう]]』『[[はっけん たいけん だいすき! しまじろう]]』『[[しまじろうヘソカ]]』『しまじろうのわお!』に登場するキャラクター<ref>{{Twitter status|shimajiroTV|41419947422916608}}</ref>\n* 生年不明 - [[ダイヤモンド (ポケットモンスターSPECIAL)|ダイヤモンド]]、漫画『[[ポケットモンスターSPECIAL]]』の主人公の1人<ref>[http://family.shogakukan.co.jp/kids/netkun/pokemon/official/ ポケットモンスターSPECIAL オフィシャルウェブサイト]</ref>\n* 生年不明 - トクサ、漫画『[[D.Gray-man]]』に登場するキャラクター<ref>[[星野桂]] 『D.Gray-man キャラクター ランキングブック キャラグレ!』 [[集英社]]〈[[ジャンプ・コミックス]]〉、2011年、163頁、ISBN 978-4-08-870268-1。</ref>\n* 生年不明 - 飛竹トンボ、漫画『[[NARUTO -ナルト-]]』に登場するキャラクター<ref>{{Cite book |和書 |author = [[岸本斉史]] |year = 2002 |title = NARUTO -ナルト- ［秘伝・臨の書］ キャラクター オフィシャルデータ BOOK |page = 77 |publisher = 集英社 |series = ジャンプ・コミックス |isbn = 4-08-873288-X }}</ref>\n* 生年不明 - 花刈ジン太、漫画・アニメ『[[BLEACH]]』に登場するキャラクター<ref>{{Cite book |和書 |author = [[久保帯人]] |year = 2006 |title = BLEACH OFFICIAL CHARACTER BOOK SOULs. |page = 47 |publisher = 集英社 |series = ジャンプ・コミックス |isbn = 4-08-874079-3 }}</ref>\n* 生年不明 - 福永葵、アダルトアニメ『[[一緒にHしよっ 〜結衣&葵編〜]]』に登場するキャラクター{{要出典|date=2018年3月29日 (木) 15:29 (UTC)}}\n* 生年不明 - [[アイドルマスター シンデレラガールズ#ヘレン|ヘレン]]、ゲーム『[[アイドルマスター シンデレラガールズ]]』に登場するキャラクター<ref>ゲーム内のプロフィールより。</ref>\n* 生年不明 - [[しまじろうシリーズの登場キャラクター#にゃっきい|桃山にゃっきい]]、ベネッセの教材『[[こどもちゃれんじ]]』、アニメ『[[しまじろうのわお!]]』に登場するキャラクター<ref>[http://kodomo.benesse.ne.jp/open/tv/characters/ しまじろうと　ちゃれんじじまの　なかまたち - しまじろうクラブ]、ベネッセグループ公式サイト。（2016/5/18閲覧）</ref>\n* 生年不明 - クラピカ、漫画・アニメ『[[HUNTER×HUNTER]]』に登場するキャラクター{{要出典|date=2018年5月}}\n\n== 出典 ==\n{{脚注ヘルプ}}\n{{Reflist}}\n\n== 関連項目 ==\n{{commons&cat|April 4|4 April}}\n{{新暦365日|4|3|4|5|[[3月4日]]|[[5月4日]]|[[4月4日 (旧暦)|4月4日]]|0404|4|04}}\n{{1年の月と日}}"}}}]}]}}