{"batchcomplete":true,"query":{"pages":[{"pageid":5433,"ns":0,"title":"11月9日","revisions":[{"slots":{"main":{"contentmodel":"wikitext","contentformat":"text/x-wiki","content":"{{カレンダー 11月}}\n'''11月9日'''（じゅういちがつここのか）は[[グレゴリオ暦]]で年始から313日目（[[閏年]]では314日目）にあたり、年末まであと52日ある。\n\n== できごと ==\n* [[1180年]]（[[治承]]4年[[10月20日 (旧暦)|10月20日]]）- [[治承・寿永の乱]]: [[富士川の戦い]]\n* [[1494年]] - [[メディチ家]]が[[フィレンツェ]]から追放される。\n* [[1799年]]（[[フランス革命暦]]ブリュメール18日） - [[フランス革命]]: [[ブリュメールのクーデタ]]。[[ナポレオン・ボナパルト|ナポレオン]]が軍事クーデターを起こし[[総裁政府]]を倒す。フランス革命が終焉。\n* [[1867年]]（[[慶応]]3年[[10月14日 (旧暦)|10月14日]]） - [[徳川慶喜]]が[[二条城]]で[[大政奉還]]を宣言。\n* [[1888年]] - [[切り裂きジャック]]が[[売春婦]]のメアリー・ジェイン・ケリーを殺害。確実に切り裂きジャックの犯行とされる最後の事件。\n* [[1907年]] - 世界最大の[[ダイヤモンド]]原石「[[カリナン]]」が[[イギリス]]国王[[エドワード7世 (イギリス王)|エドワード7世]]に贈られる。\n* [[1918年]] - [[ドイツ革命]]: 皇帝[[ヴィルヘルム2世 (ドイツ皇帝)|ヴィルヘルム2世]]が[[オランダ]]に亡命。[[ドイツ社会民主党|社会民主党]]の[[フィリップ・シャイデマン]]が[[共和政]]の樹立を宣言。\n* [[1923年]] - [[ミュンヘン一揆]]が鎮圧。\n* [[1925年]] - [[親衛隊 (ナチス)|ナチス親衛隊]] (SS) が発足。\n* [[1935年]] - 上海で[[中山水兵射殺事件]]。\n* [[1935年]] - {{仮リンク|アメリカ産業別労働組合会議|en|Congress of Industrial Organizations}}(CIO)設立。\n* [[1938年]] - [[水晶の夜]]（クリスタルナハト）。この日の夜から翌日未明にかけてドイツ各地でユダヤ人に対する襲撃が行われる。\n* [[1945年]] - 旧[[立憲政友会]]を中心に[[日本自由党 (1945-1948)|日本自由党]]を結成。\n* [[1953年]] - [[カンボジア]]が[[フランス]]から独立。\n* [[1960年]] - [[フォード・モーター]]の社長に、初めてフォード家以外の人物である[[ロバート・マクナマラ]]が就任。\n* [[1962年]] - [[廖承志]]と[[高碕達之助]]が「日中長期総合貿易に関する覚書」（[[LT貿易]]覚書）に調印。\n* [[1963年]] - [[鶴見事故]]。横浜市鶴見区の[[東海道貨物線]]で貨物列車が脱線。[[東海道本線|東海道線]]上下線の旅客列車の多重衝突事故を引き起こし、死者161人。\n* 1963年 - [[三井三池三川炭鉱炭じん爆発]]。死者458人。\n* [[1964年]] - [[池田勇人]]首相が病気により辞任。[[第1次佐藤内閣|第1次佐藤榮作内閣]]が発足し[[第3次池田内閣 (改造)|池田内閣]]の全閣僚を再任。\n* [[1965年]] - [[1965年北アメリカ大停電]]\n* [[1967年]] - [[アメリカ航空宇宙局|NASA]]の[[サターンV]]ロケットの初の発射実験として無人宇宙機「[[アポロ4号]]」が打ち上げ。\n* 1967年 - [[武満徹]]作曲の『[[ノヴェンバー・ステップス]]』が[[ニューヨーク]]で初演。\n* 1967年 - 米軍が押収していた[[原子爆弾|原爆]]記録映画が22年ぶりに日本に返還。\n* [[1974年]] - 東京湾で[[液化石油ガス|LPG]]・石油タンカー「第十雄洋丸」が衝突炎上事故を起こす。（[[第十雄洋丸事件]]）\n* [[1985年]] - 22歳の[[ガルリ・カスパロフ]]が[[アナトリー・カルポフ]]を破り、史上最年少の[[チェス]]の世界チャンピオンとなる。\n<!-- 前日の発生で * [[1986年]] - [[杉並一家放火殺人事件]]の指名手配犯が逮捕される。 -->\n* [[1987年]] - [[東京ドーム]]建設のため、[[後楽園球場]]の解体を開始。\n* [[1989年]] - [[ベルリンの壁崩壊]]: 東西ドイツの[[国境検問所]]で市民の通行が自由化。\n* 1989年 - [[トウ小平|鄧小平]]が、最後のポストである[[中国共産党中央軍事委員会]]主席から引退。\n* [[1994年]] - [[ドイツ]]・[[ダルムシュタット]]の[[重イオン研究所]]で110番原子[[ダームスタチウム]]が発見される。\n* [[2004年]] - [[Mozilla Firefox|Firefox]] 1.0リリース。\n* [[2005年]] - [[欧州宇宙機関]] (ESA) の[[金星]]探査機「[[ビーナス・エクスプレス]]」が打ち上げ。\n<!-- 一々書いているとキリがない * [[2006年]] - [[水星]]が太陽の前を[[日面通過]]。 -->\n<!-- * [[2008年]] - [[日本選手権シリーズ|日本シリーズ]]で[[埼玉西武ライオンズ]]が[[読売ジャイアンツ]]を4勝3敗で下し、4年振り13回目の日本一に。[[渡辺久信]]監督は史上8人目の新人日本一監督に。 -->\n\n== 誕生日 ==\n[[ファイル:Noguchi Hideyo.jpg|thumb|140px|細菌学者[[野口英世]](1876-1928)誕生。[[黄熱病]]や[[梅毒]]などの研究で知られる細菌学及び医学的の権威。]]\n* [[1731年]] - [[ベンジャミン・バネカー]]、[[天文学者]]（+ [[1806年]]）\n* [[1818年]] - [[イワン・ツルゲーネフ]]、[[小説家]]（+ [[1883年]]）\n* [[1834年]]（[[天保]]5年[[10月9日 (旧暦)|10月9日]]） - [[近藤勇]]、[[新選組|新撰組]]局長（+ [[1868年]]）\n* [[1841年]] - [[エドワード7世 (イギリス王)|エドワード7世]]、[[イギリス君主一覧|イギリス王]]（+ [[1910年]]）\n* [[1864年]] - [[ポール・セリュジエ]]、[[画家]]（+ [[1927年]]）\n* [[1876年]] - [[野口英世]]、細菌学者（+ [[1928年]]）\n* [[1877年]] - [[ムハンマド・イクバール]]、詩人、哲学者、政治家（+ [[1938年]]）\n* [[1883年]] - [[伊勢ノ濱慶太郎]]、[[大相撲]]の[[力士]]（+ [[1928年]]）\n* 1883年 - [[チャールズ・デムス]]、画家（+ [[1935年]]）\n* [[1922年]] - [[若葉山貞雄]]、力士（+ [[2001年]]）\n* 1922年 - [[高村章子]]、[[声優]]（+ [[2012年]]）\n* [[1930年]] - [[イヴァン・モラヴェッツ]]、[[ピアニスト]]（+ [[2015年]]）\n* [[1931年]] - [[白石一郎]]、[[作家]]（+ [[2004年]]）\n* 1931年 - [[山内久司]]、[[朝日放送]][[テレビプロデューサー]]（+ [[2014年]]）\n* 1931年 - [[ホワイティ・ハーゾグ]]、[[メジャーリーガー]]、監督\n* [[1933年]] - [[ダークダックス|高見澤宏]]、[[ダークダックス]]のトップ・[[テナー]]（+ [[2011年]]）\n* [[1934年]] - [[カール・セーガン]]、[[天文学者]]、作家（+ [[1996年]]）\n* 1934年 - [[花村えい子]]、[[漫画家]]、[[芸術家]]\n* 1934年 - [[ロナルド・ハーウッド]]、[[脚本家]]\n* 1934年 - [[杉尾富美雄]]、[[プロ野球選手]]（+ [[2002年]]）\n* [[1935年]] - [[ボブ・ギブソン]]、元[[メジャーリーグベースボールの選手一覧|メジャーリーガー]]\n* [[1936年]] - [[ミハイル・タリ]]、第10代[[チェスの世界チャンピオン一覧|チェスの公式世界チャンピオン]]（+ [[1992年]]）\n* 1936年 - [[マリー・トラヴァース]]、[[ミュージシャン]]（[[ピーター・ポール&マリー]]）（+ [[2009年]]）\n* [[1937年]] - [[牧野宏]]、プロ野球選手（+ [[1994年]]）\n* [[1939年]] - [[佐川満男]]、[[俳優]]\n* 1939年 - [[アラン・ジレッティ]]、[[フィギュアスケート]]選手\n* [[1940年]] - [[正司敏江・玲児|正司敏江]]、[[漫才師]]\n* [[1945年]] - [[後原富]]、プロ野球選手、高校野球指導者\n* [[1947年]] - [[ルイス・フェリペ・スコラーリ]]、元[[サッカー選手]]、[[サッカー]]指導者\n* [[1948年]] - [[門野利治]]、プロ野球選手\n* [[1950年]] - [[梅沢富美男]]、俳優\n* [[1952年]] - [[ジャック・W・ショスタク]]、[[生物学者]]\n* 1952年 - [[ジム・リグルマン]]、[[メジャーリーグ]]監督\n* [[1954年]] - [[亀山助清]]、声優（+ [[2013年]]）\n* [[1955年]] - [[遥くらら]]、女優\n* 1955年 - [[平田恒雄]]、元プロ野球選手（+ [[2016年]]）\n* [[1957年]] - [[宮本尊義]]、プロ野球選手\n* [[1959年]] - [[長島哲郎]]、プロ野球選手\n* [[1960年]] - [[石田えり]]、[[俳優|女優]]\n*1960年 - [[徐河辰]]、小説家\n* [[1961年]] - [[坂本佳一]]、[[野球選手]]\n* [[1962年]] - [[高倉あつこ]]、漫画家\n* 1962年 - [[ディオン・ジェームズ]]、元プロ野球選手\n* 1962年 - [[世耕弘成]]、政治家\n* [[1965年]] - [[旭里憲治]]、元大相撲力士、年寄[[中川 (相撲)|中川]]\n* [[1967年]] - [[森山佳郎]]、元サッカー選手、サッカー指導者\n* [[1969年]] - [[小嶋敬二]]、[[競輪選手]]、[[自転車競技]]選手\n* [[1970年]] - [[クリス・ジェリコ]]、[[プロレスラー]]\n* [[1971年]] - [[デビッド・デュバル]]、[[プロゴルファー一覧|プロゴルファー]]\n* 1971年 - [[ジョナサン・ナナリー]]、元プロ野球選手\n* [[1972年]] - [[進藤尚美]]、声優\n* [[1973年]] - [[ニック・ラシェイ]]、[[歌手]]\n* 1973年 - [[上田浩二郎]]、お笑い芸人（[[Hi-Hi]]）\n* [[1974年]] - [[アレッサンドロ・デル・ピエロ]]、[[サッカー選手]]\n* 1974年 - [[加瀬亮]]、俳優\n* 1974年 - [[TOSHI-LOW]]、ミュージシャン、[[BRAHMAN]]\n* [[1976年]] - [[栃東大裕]]、元[[大関]]\n* [[1978年]] - [[ジェイソン・スタンリッジ]]、プロ野球選手\n* [[1979年]] - [[庄田隆弘]]、プロ野球選手\n* 1979年 - [[アダム・ダン]]、メジャーリーガー\n* 1979年 - [[三宅梢子]]、[[タレント]]\n* 1979年 - [[福田恵悟]]、お笑い芸人 ([[LLR (お笑いコンビ)|LLR]])\n* [[1980年]] - [[鬼崎智史]]、野球選手\n* [[1981年]] - [[田淵裕章]]、[[フジテレビジョン|フジテレビ]][[アナウンサー]]\n* 1981年 - [[大口兼悟]]、[[俳優]]\n* [[1982年]] - [[アンディ・サワー]]、[[シュートボクシング|シュートボクサー]]\n* 1982年 - 山田雅人、ミュージシャン（[[シュノーケル (バンド)|シュノーケル]]）\n* 1982年 - [[エミリー・ヌッシーア]]、[[フィギュアスケート]]選手\n* 1982年 - [[志村亜貴子]]、[[野球選手]]\n* 1982年 - [[菊池こころ]]、[[声優]]\n* [[1983年]] - [[宮島咲良]]、[[モデル (職業)|モデル]]、[[フリーアナウンサー]]、タレント、歌手\n* 1983年 - [[D-51#メンバー|YU]]、男性歌手\n* 1983年 - [[トニー・バーネット]]、メジャーリーガー\n* [[1984年]] - [[えなりかずき]]、タレント\n* 1984年 - 尾崎世界観、歌手（[[クリープハイプ]]）\n* 1984年 - [[城田純]]、[[デザイナー]]、モデル、歌手\n* 1984年 - [[ジョエル・ズマヤ]]、メジャーリーガー\n* 1984年 - [[SE7EN]]、歌手\n* 1984年 - [[ク・ヘソン]]、[[俳優|女優]]\n* 1984年 - [[デルタ・グッドレム]]、[[シンガー・ソングライター]]、[[ピアニスト]]、女優\n* [[1985年]] - [[大島洋平]]、プロ野球選手\n* 1985年 - [[福島彩乃]]、[[北陸放送]]アナウンサー\n<!-- 出典が不明 * [[1985年]] - [[朋未]]、プラモドル -->\n* 1986年 - [[アンドリュー・キャッシュナー]]、メジャーリーガー\n* [[1987年]] - [[村田綾]]、女優、[[アイドル]]\n* 1987年 - [[林明寛]]、俳優\n* [[1988年]] - [[草場恵]]、[[グラビアアイドル]]\n* 1988年 - [[伊藤将大]]、サッカー選手\n* [[1989年]] - [[宇田川ひとみ]]、グラビアアイドル\n* [[1990年]] - [[ノサ・イギエボー]]、サッカー選手\n* [[1991年]] - 碧みさき、アイドル（[[JK21]]）\n* 1991年 - [[宮田麻里乃]]、[[ミス日本]]グランプリ\n* [[1992年]] - [[グレッグ・バード (野球)|グレッグ・バード]]、メジャーリーガー\n* 1992年 - [[大坂谷啓生]]、プロ野球選手\n* 1992年 - [[酒井宣福]]、[[サッカー]]選手\n* [[1993年]] - [[江原美優]]、女優、ファッションモデル\n* [[1995年]] - [[杉原千尋]]、フジテレビアナウンサー\n* [[1996年]] - モモ、アイドル（[[TWICE (韓国の音楽グループ)|TWICE]]）\n* [[1997年]] - [[野元空]]、アイドル（[[フェアリーズ]]）\n* [[1998年]] - [[佐藤麗奈]]、タレント、アイドル（[[マジカル・パンチライン]]）\n* 1998年 - [[鈴木理子 (キリンプロ)|鈴木理子]]、女優\n* [[2003年]] - [[長尾しおり]]、アイドル（[[SUPER☆GiRLS]]）\n* 生年不明 - [[坂本一]]、声優\n* 生年不明 - [[植村友美]]、声優\n* 生年不明 - [[笠原あきら]]、声優\n\n== 忌日 ==\n* [[959年]] - [[コンスタンティノス7世]]、[[東ローマ帝国|東ローマ皇帝]]（* [[905年]]?）\n* [[1187年]]（[[淳熙]]14年10月8日） - [[高宗 (宋)|高宗]]、[[中国]][[南宋]]初代[[皇帝]]（* [[1108年]]）\n* [[1388年]]（[[元中]]5年/[[嘉慶 (日本)|嘉慶]]2年[[10月2日 (旧暦)|10月2日]]） - [[春屋妙葩]]、[[僧]]（* [[1311年]]）\n* [[1504年]] - [[フェデリーコ1世 (ナポリ王)|フェデリーコ1世]]、[[ナポリ王国|ナポリ王]]（* [[1452年]]）\n* [[1550年]]（[[天文 (元号)|天文]]19年[[10月1日 (旧暦)|10月1日]]） - [[横田高松]]、[[武将|戦国武将]]\n* [[1573年]]（[[天正]]元年[[10月15日 (旧暦)|10月15日]]） - [[島津勝久]]、[[薩摩国]]の[[戦国大名]]（* [[1503年]]）\n* [[1613年]]（[[慶長]]18年[[9月27日 (旧暦)|9月27日]]） - [[大久保忠佐]]、戦国武将、[[沼津藩|沼津藩主]]（* [[1537年]]）\n* [[1630年]]（[[寛永]]7年[[10月5日 (旧暦)|10月5日]]） - [[藤堂高虎]]、初代[[津藩|津藩主]]（* [[1556年]]）\n* [[1641年]] - [[フェルナンド・デ・アウストリア (枢機卿)|枢機卿フェルナンド]]、[[南ネーデルラント|スペイン領ネーデルラント]]総督（* [[1609年]]）\n*[[1677年]] - [[アールト・ファン・デル・ネール]]、画家（* [[1603年]]頃）\n* [[1699年]] - [[オルタンス・マンチーニ]]、[[イングランド王国|イングランド王]][[チャールズ2世 (イングランド王)|チャールズ2世]]の愛妾（* [[1646年]]）\n* [[1724年]]（[[享保]]9年[[9月24日 (旧暦)|9月24日]]） - [[西川如見]]、[[天文学者]]（* [[1648年]]）\n* [[1766年]] - [[ウニコ・ヴィルヘルム・ファン・ヴァッセナール]]、[[作曲家]]（* [[1692年]]）\n* [[1769年]]（[[明和]]6年[[10月12日 (旧暦)|10月12日]]） - [[青木昆陽]]、[[蘭学|蘭学者]]（* [[1698年]]）\n* [[1773年]]（[[安永 (元号)|安永]]2年[[9月25日 (旧暦)|9月25日]]） - [[吉益東洞]]、[[漢方医学|漢方医]]（* [[1702年]]）\n* [[1778年]] - [[ジョヴァンニ・バッティスタ・ピラネージ]]、[[版画家]]、[[建築家]]（* [[1720年]]）\n* [[1856年]] - [[ジョン・ミドルトン・クレイトン (国務長官)|ジョン・ミドルトン・クレイトン]]、[[アメリカ合衆国国務長官]]（* [[1796年]]）\n* [[1873年]] - [[スティーヴン・マロリー]]、[[アメリカ連合国]]海軍長官（* [[1813年]]）\n* [[1892年]] - [[ジョージ・スペンサー＝チャーチル (第8代マールバラ公)]]、イギリスの貴族（* [[1844年]]）\n* [[1909年]] - [[ウィリアム・フリス]]、[[画家]]（* [[1819年]]）\n* [[1910年]] - [[大塚楠緒子]]、[[歌人]]（* [[1875年]]）\n* [[1917年]] - [[マッジ・サイアーズ]]、[[フィギュアスケート]]選手（* [[1881年]]）\n* [[1918年]] - [[ギヨーム・アポリネール]]、[[詩人]]（* [[1880年]]）\n* [[1924年]] - [[ヘンリー・カボット・ロッジ]]、[[アメリカ合衆国上院|アメリカ合衆国上院議員]]（* [[1850年]]）\n* [[1927年]] - [[南条文雄]]、[[仏教学者]]（* [[1849年]]）\n* [[1929年]] - [[斎藤秀三郎]]、[[英語学|英語学者]]（* [[1866年]]）\n* [[1930年]] - [[浅野総一郎]]、[[実業家]]、[[浅野財閥]]創業者（* [[1848年]]）\n* [[1932年]] - [[ナジェージダ・アリルーエワ]]、[[ソビエト連邦]]指導者[[ヨシフ・スターリン|スターリン]]の妻（* [[1901年]]）\n* [[1937年]] - [[ラムゼイ・マクドナルド]]、[[イギリスの首相|イギリス首相]]（* [[1866年]]）\n* [[1938年]] - [[ヴァシーリー・ブリュヘル]]、[[ソ連邦元帥]]（* [[1889年]]）\n* [[1940年]] - [[ネヴィル・チェンバレン]]、第60代イギリス首相（* [[1869年]]）\n* [[1944年]] - [[フランク・マーシャル (チェスプレーヤー)|フランク・マーシャル]]、[[チェス]]プレーヤー（* [[1877年]]）\n* 1944年 - [[ラドノーティ・ミクローシュ]]、詩人（* [[1909年]]）\n* [[1951年]] - [[シグマンド・ロンバーグ]]、作曲家（* [[1887年]]）\n* [[1952年]] - [[ハイム・ヴァイツマン]]、初代[[イスラエルの大統領|イスラエル大統領]]（* [[1874年]]）\n* [[1953年]] - [[アブドゥルアズィーズ・イブン＝サウード]]、初代[[サウジアラビア]]国王（* [[1880年]]）\n* 1953年 - [[ディラン・トーマス]]、詩人（* [[1914年]]）\n* [[1959年]] - [[竹脇昌作]]、[[アナウンサー]]（* [[1910年]]）\n* [[1961年]] - [[正田貞一郎]]、実業家、[[日清製粉]]創業者（* [[1870年]]）\n* [[1963年]] - [[勝沼精蔵]]、[[医学者]]（* [[1886年]]）\n* 1963年 - [[三枝博音]]、[[哲学者]]（* [[1892年]]）\n* [[1966年]] - [[小沢治三郎]]、第31代[[連合艦隊司令長官]]（* 1886年）\n* [[1970年]] - [[シャルル・ド・ゴール]]、[[フランスの大統領|フランス大統領]]（* [[1890年]]）\n* 1970年 - [[川島正次郎]]、元[[自由民主党幹事長]]・[[自由民主党副総裁|副総裁]]、[[専修大学]]学長（* [[1890年]]）\n* [[1976年]] - [[ゴットフリート・フォン・クラム]]、[[テニス]]選手（* [[1909年]]）\n* 1976年 - [[ロジーナ・レヴィーン]]、[[ピアニスト]]、ピアノ教師（* [[1880年]]）\n* [[1980年]] - [[白井喬二]]、[[小説家]]（* [[1889年]]）\n* [[1981年]] - [[山川武範]]、[[プロ野球選手]]（* [[1922年]]）\n* 1981年 - [[フランク・マリナ]]、航空技師、[[画家]]（* [[1912年]]）\n* [[1987年]] - [[ヴラディーミル・ルジャク]]、[[バリトン]]（* [[1912年]]）\n* [[1988年]] - [[茅誠司]]、[[物理学者]]、[[小さな親切運動]]提唱者（* [[1898年]]）\n* 1988年 - [[ジョン・N・ミッチェル]]、元[[アメリカ合衆国司法長官]]（* [[1913年]]）\n* [[1991年]] - [[イヴ・モンタン]]、[[俳優]]、[[シャンソン]][[歌手]] （* [[1921年]]）\n* [[1995年]] - [[ルイ・マル]]、[[映画監督]]（* [[1932年]]）\n* [[1998年]] - [[若生忠男]]、プロ野球選手（* [[1936年]]）\n* [[1999年]] - [[八木義徳]]、小説家（* [[1911年]]）\n* [[2000年]] - [[東千代之介]]、俳優（* [[1926年]]）\n* 2000年 - [[茶川一郎]]、俳優（* [[1927年]]）\n* [[2001年]] - [[ジョヴァンニ・レオーネ]]、第6代[[共和国大統領 (イタリア)|イタリア大統領]]（* [[1908年]]）\n* 2001年 - [[千葉耕市]]、[[声優]]、[[音響監督]] （* [[1931年]]）\n* [[2004年]] - [[アイリス・チャン]]、ジャーナリスト（* [[1968年]]）\n* [[2005年]] - [[コチェリル・ラーマン・ナラヤナン]]、第10代[[インドの大統領|インド大統領]]（* [[1921年]]）\n* [[2006年]] - [[マルクス・ヴォルフ]]、旧[[ドイツ民主共和国|東ドイツ]]の対外諜報総局長（* [[1923年]]）\n* [[2007年]] - [[天城一]]、小説家、[[数学者]]（* [[1919年]]）\n* [[2008年]] - [[佐田武夫]]、実業家（* [[1925年]]）\n* 2008年 - [[チャンバラトリオ|前田竹千代]]、[[コメディアン]]（チャンバラトリオ）（* [[1952年]]）\n* [[2011年]] - [[黒沢良]]、声優、俳優（* [[1930年]]）\n* [[2013年]] - [[三木谷良一]]、[[経済学者]]（* [[1929年]]）\n* [[2015年]] - [[トミー・ハンソン]]、[[プロ野球選手]]（* [[1986年]]）\n* [[2016年]] - [[石黒修]]、元プロ[[テニス選手]]（* [[1936年]]）\n\n== 記念日・年中行事 ==\n*[[ウクライナ語の日]]（{{UKR}}）\n* [[建国記念日|独立記念日]]（{{KHM}}）\n*: [[1953年]]のこの日、カンボジアが[[フランス]]から独立した。\n* [[ムハンマド・イクバール]]誕生日（{{PAK}}）\n*: 詩人・哲学者で、[[1930年]]に初めてインドにおけるイスラム国家樹立を主張したムハンマド・イクバールの[[1877年]]の誕生日を記念。\n* [[発明家の日]]（{{DEU}}・{{AUT}}・{{CHE}}）\n*: オーストリア出身の女優で発明家の[[ヘディ・ラマー]]の[[1914年]]の誕生日を記念。\n* [[運命の日]]（{{DEU}}）\n*: ドイツの20世紀史上、重大事件がしばしば起きた[[特異日]]としての11月9日。[[特異日#政治史]]\n* [[換気]]の日（{{JPN}}）\n*: [[日本電機工業会]]が[[1987年]]に制定。「いい(11)く(9)うき」（いい空気）の語呂合せ。\n* [[119番の日]]（{{JPN}}）\n*: [[消防庁]]が[[1987年]]に制定。消防の[[緊急通報用電話番号]]が[[119番]]であることから。また、この日から[[11月15日]]までの1週間は[[火災予防運動|秋の全国火災予防運動]]が行われる。\n\n* 太陽暦採用記念日（{{JPN}}）\n*: [[明治]]5年[[11月9日 (旧暦)|11月9日]]（[[旧暦]]）に、それまでの[[太陰太陽暦]]をやめて[[太陽暦]]を採用するという布告が行われたことに由来。\n\n== フィクションのできごと ==\n{{フィクションの出典明記|section=1|ソートキー=日1109|date=2011年7月}}\n\n=== 誕生日（フィクション） ===\n* [[1977年]] - 宇生田広数、漫画・アニメ『[[DEATH NOTE]]』に登場するキャラクター<ref>[[大場つぐみ]]、[[小畑健]]『[[DEATH NOTE]]』13巻、[[集英社]]、2006年、23頁、ISBN 978-4-08-874095-9。</ref>\n* [[1991年]] - 清滝桂香、小説・漫画・アニメ『[[りゅうおうのおしごと!]]』に登場するキャラクター<ref>{{Cite book|和書|title=[[りゅうおうのおしごと!]]|volume=1|author=[[白鳥士郎]]|publisher=[[SBクリエイティブ]]|page=179|isbn=978-4-7973-8484-0}}</ref><ref>{{Cite book|和書|title=[[りゅうおうのおしごと!]]|volume=1|author=[[白鳥士郎]]|publisher=[[SBクリエイティブ]]|page=213|isbn=978-4-7973-8484-0}}</ref>\n* [[1998年]] - 天王寺綯、ゲーム・アニメ『[[STEINS;GATE]]』『[[ROBOTICS;NOTES]]』に登場するキャラクター<ref>『ROBOTICS;NOTES 【ロボティクス・ノーツ】 公式設定資料集：Childhood Dreams』 [[アスキー・メディアワークス]]、2012年、84頁、ISBN 978-4-04-886756-6。</ref>\n* 生年不明 - 長谷川日向子、アニメ『[[多田くんは恋をしない]]』に登場するキャラクター<ref>{{Cite web |url=http://tadakoi.tv/chara06.html |title=長谷川日向子｜キャラクター |accessdate=2018-6-28 |work=多田くんは恋をしない 公式サイト}}</ref>\n* 生年不明 - [[海賊 (ONE PIECE)#ベン・ベックマン|ベン・ベックマン]] 、漫画・アニメ『[[ONE PIECE]]』に登場するキャラクター<ref>{{Cite book |和書 |author = [[尾田栄一郎]] |year = 2012 |title = ONE PIECE BLUE DEEP CHARACTERS WORLD |page = 159 |publisher = 集英社 |series = ジャンプ・コミックス |isbn = 978-4-08-870445-6 }}</ref>\n* 生年不明 - 斑目一角、漫画・アニメ『[[BLEACH]]』に登場するキャラクター<ref>[[久保帯人]] 『BLEACH OFFICIAL CHARACTER BOOK SOULs.』 集英社〈[[ジャンプ・コミックス]]〉、2006年、116頁、ISBN 4-08-874079-3。</ref>\n\n== 出典 ==\n{{脚注ヘルプ}}\n{{Reflist}}\n\n== 関連項目 ==\n{{commonscat|9 November}}\n{{新暦365日|11|8|11|10|[[10月9日]]|[[12月9日]]|[[11月9日 (旧暦)|11月9日]]|1109|11|09}}\n{{1年の月と日}}"}}}]}]}}