{"batchcomplete":true,"query":{"pages":[{"pageid":5562,"ns":0,"title":"11月20日","revisions":[{"slots":{"main":{"contentmodel":"wikitext","contentformat":"text/x-wiki","content":"{{カレンダー 11月}}\n'''11月20日'''（じゅういちがつはつか、じゅういちがつにじゅうにち）は[[グレゴリオ暦]]で年始から324日目（[[閏年]]では325日目）にあたり、年末まであと41日ある。\n\n== できごと ==\n* [[1578年]]（[[天正]]6年[[10月21日 (旧暦)|10月21日]]） - [[織田信長]]に帰属していた[[荒木村重]]が謀反。\n* [[1620年]]（[[ユリウス暦]][[11月11日]]） - [[メイフラワー号]]に乗ってアメリカに渡った[[ピルグリム・ファーザーズ]]が[[メイフラワー誓約]]に署名。\n* [[1805年]] - [[ルートヴィヒ・ヴァン・ベートーヴェン|ベートーヴェン]]唯一の[[オペラ]]『[[フィデリオ]]』が初演。ベートーヴェン自身が指揮をするが失敗。\n* [[1889年]] - [[グスタフ・マーラー|マーラー]]の[[交響曲第1番 (マーラー)|交響曲第1番]]が初演。\n* [[1910年]] - [[メキシコ革命]]: [[フランシスコ・マデロ]]が[[ポルフィリオ・ディアス]]大統領の大統領選での不正と当選無効を訴えて一斉蜂起。メキシコ革命が始まる。\n* [[1917年]] - [[ウクライナ]]初の近代国家となる[[ウクライナ人民共和国]]が独立を宣言。\n* [[1917年]] - [[第一次世界大戦]]: [[カンブレーの戦い]]はじまる。\n* [[1927年]] - [[御岳登山鉄道]]設立。\n* [[1934年]] - [[辻政信]]らの働きかけで、[[皇道派]]の[[村中孝次]]大尉・[[磯部浅一]]一等主計ら3人と[[陸軍士官学校]]生徒5人を[[クーデター]]謀議で逮捕。（[[陸軍士官学校事件]]）\n* [[1937年]] - [[国民政府]]（[[蒋介石政権]]）が南京から重慶への遷都を宣言。\n* [[1938年]] - [[岩波書店]]が「[[岩波新書]]」の刊行を開始。\n* [[1940年]] - [[第二次世界大戦]]: [[ハンガリー]]、[[ルーマニア]]、[[スロバキア]]が[[日独伊三国同盟]]に加盟。\n* [[1945年]] - [[ドイツ]]の[[ニュルンベルク]]で[[第二次世界大戦]]の戦犯を裁く国際軍事裁判（[[ニュルンベルク裁判]]）が始まる。\n* [[1947年]] - [[イギリス]]のエリザベス王女（後の国王[[エリザベス2世]]）と[[フィリップ (エディンバラ公)|エディンバラ公フィリップ]]が結婚。\n* 1947年 - [[任天堂]]設立。\n* [[1948年]] - 日本初の[[競輪]]が[[小倉競輪場]]で開始。\n* [[1954年]] - 神奈川県[[相模原市]]が市制施行。\n* [[1962年]] - [[京葉臨海鉄道]]設立。\n* [[1963年]] - 国連総会で[[あらゆる形態の人種差別の撤廃に関する国際連合宣言|人種差別撤廃宣言]]を採択。\n* [[1971年]] - [[中華航空825便爆破事件]]\n* [[1979年]] - [[アル＝ハラム・モスク占拠事件]]\n* [[1980年]] - [[文化大革命]]を指導した[[四人組]]の裁判が開始。\n* [[1980年]] - [[川治プリンスホテル火災]]。死者数45名。\n* [[1981年]] - [[野岩鉄道]]設立。\n* [[1985年]] - [[マイクロソフト]]が[[Microsoft Windows 1.0]]を発売。\n* [[1992年]] - [[イギリス王室]]の離宮・[[ウィンザー城]]で火災。([[1992年ウィンザー城火災]])\n* [[1998年]] - [[国際宇宙ステーション]]の最初のモジュール「[[ザーリャ]]」が[[カザフスタン]]の[[バイコヌール宇宙基地]]から打上げ。\n* 1998年 - アメリカ[[マサチューセッツ州]][[ボストン]]近郊で[[トランスジェンダー]]の{{仮リンク|リタ・ヘスター|en|Rita Hester}}が惨殺された。（[[トランスジェンダー追悼の日]]の由来）\n* [[2001年]] - [[シアトル・マリナーズ]]の[[イチロー]]が、[[メジャーリーグベースボール]]で日本人初の[[最優秀選手 (MLB)|MVP]]を獲得。\n* [[2005年]] - 日本の小惑星探査機「[[はやぶさ (探査機)|はやぶさ]]」が小惑星[[イトカワ (小惑星)|イトカワ]]の岩石の採取を試みるも失敗し、イトカワの地表に不時着。\n* [[2007年]] - 改正[[出入国管理及び難民認定法]]施行。一部の例外を除き、外国人の指紋採取・写真撮影の義務化がスタート<ref>{{Cite web |date=2008年1月10日 |url=http://www.kantei.go.jp/jp/q&a/archive/20080110a.html |title=お答えします |publisher=首相官邸 |accessdate=2018-02-12}}</ref>。\n\n== 誕生日 ==\n* [[1625年]] - [[パウルス・ポッテル]]、[[画家]]（+ [[1654年]]）\n* [[1696年]]（[[元禄]]9年[[10月26日 (旧暦)|10月26日]]） - [[徳川宗春]]、第7代[[尾張藩|尾張藩主]]（+ [[1764年]]）\n* [[1752年]] - [[トーマス・チャタートン]]、[[詩人]]（+ [[1770年]]）\n* [[1753年]] - [[ルイ＝アレクサンドル・ベルティエ]]、[[軍人]]（+ [[1815年]]）\n* [[1803年]]（[[ユリウス暦]][[11月8日]]） - [[エフィム・プチャーチン]]、海軍将官（+ [[1883年]]）\n* [[1843年]]（[[天保]]14年閏[[9月29日 (旧暦)|9月29日]]） - [[品川弥二郎]]、[[長州藩|長州藩士]]・[[政治家]]（+ [[1900年]]）\n* [[1851年]] - [[マルゲリータ・ディ・サヴォイア＝ジェノヴァ]]、[[イタリア王国|イタリア]]王妃（+ [[1926年]]）\n* [[1858年]] - [[セルマ・ラーゲルレーヴ]]、[[小説家]]（+ [[1940年]]）\n* [[1862年]] - [[ジョルジュ・パラント]]、[[思想]]家、[[哲学|哲学者]]（+ [[1925年]]）\n* 1862年 - [[エドワード・ウェスターマーク]]、哲学者、[[社会学者の一覧|社会学者]]（+ [[1939年]]）\n* 1862年 - [[ダン・ケイシー]]、[[メジャーリーガー]]（+ [[1943年]]）\n* [[1866年]] - [[ケネソー・マウンテン・ランディス]]、MLB[[コミッショナー]]（+ [[1944年]]）\n* [[1869年]] - [[クラーク・グリフィス]]、メジャーリーガー（+ [[1955年]]）\n* [[1871年]] - [[ウィリアム・ヒアド・キルパトリック]]、[[教育学|教育学者]]（+ [[1965年]]）\n* [[1886年]] - [[カール・フォン・フリッシュ]]、動物行動学者（+ [[1982年]]）\n* [[1889年]] - [[エドウィン・ハッブル]]、[[天文学者]]（+ [[1953年]]）\n* 1889年 - [[中井一夫]]、[[裁判官]]、[[弁護士]]、[[政治家]]（+ [[1991年]]）\n* 1889年 - [[小野竹喬]]、[[日本画家]]（+ [[1979年]]）\n* [[1892年]] - [[末川博]]、[[民法]]学者（+ [[1977年]]）\n* [[1896年]] - [[林達夫]]、[[思想]]家、[[評論家]]（+ [[1984年]]）\n* [[1897年]] - [[中島清次郎]]、[[寿司職人]]（+ [[1972年]]）\n* [[1899年]] - [[田嶋一雄]]、[[実業家]]、[[ミノルタ|ミノルタカメラ]]創業者（+ [[1985年]]）\n* [[1903年]] - [[アレクサンドラ・ダニロワ]]、[[バレエ]]ダンサー（+ [[1997年]]）\n* [[1904年]] - [[中馬馨]]、[[政治家]]、第13代[[大阪市長]]（+ [[1971年]]）\n* [[1907年]] - [[アンリ＝ジョルジュ・クルーゾー]]、[[映画監督]]（+ [[1977年]]）\n* [[1912年]] - [[オットー・フォン・ハプスブルク]]、[[ハプスブルク家]]当主（+ [[2011年]]）\n* [[1913年]] - [[ヤコフ・ザーク]]、[[ピアニスト]]（+ [[1976年]]）\n* [[1914年]] - [[エミリオ・プッチ]]、[[ファッションデザイナー]]、政治家（+ [[1992年]]）\n* 1914年 - [[見坊豪紀]]、[[日本語学|国語学]]者（+ [[1992年]]）\n* [[1915年]] - [[市川崑]]、[[映画監督]]（+ [[2008年]]）\n* 1915年 - [[庄野英二]]、[[児童文学|児童文学者]]（+ [[1993年]]）\n* 1915年 - [[胡耀邦]]、[[政治家]]、[[中国共産党]]総書記・党主席（+ [[1989年]]）\n* [[1922年]] - [[ノエル・ミュートン＝ウッド]]、[[ピアニスト]]、[[作曲家]]（+ [[1953年]]）\n* 1922年 - [[野村泰治]]、アナウンサー（+ [[2002年]]）\n* [[1923年]] - [[ナディン・ゴーディマー]]、作家 (+ [[2014年]])\n* [[1924年]] - [[ブノワ・マンデルブロ]]、[[数学者]]（+ [[2010年]]）\n* [[1925年]]  - [[ロバート・ケネディ]]、政治家（+ [[1968年]]）\n* 1925年 - [[マイヤ・プリセツカヤ]]、[[バレエ]]ダンサー（+ [[2015年]]）\n* 1925年 - [[三木久一]]、[[プロ野球選手]]（+ [[1948年]]）\n* [[1926年]] - [[根本陸夫]]、プロ野球選手、[[プロ野球監督]]（+ [[1999年]]）\n* 1926年 - [[赤羽賢司]]、[[天文学者]]（+ [[2015年]]）\n* [[1932年]] - [[内藤ルネ]]、[[イラストレーター]]（+ [[2007年]]）\n* 1932年 - [[萬屋錦之介]]、[[俳優]]（+ [[1997年]]）\n* [[1934年]] - [[配島久美]]、プロ野球選手\n* [[1936年]] - [[ドン・デリーロ]]、[[小説家]]、[[劇作家]]\n* [[1937年]] - [[ルース・ラレード]]、[[ピアニスト]]（+ [[2005年]]）\n* [[1941年]] - [[清國勝雄]]、元大相撲力士、元年寄[[伊勢ヶ濱]]\n* 1941年 - [[前川芳男]]、[[プロ野球審判員]]\n* [[1942年]] - [[大沢昇]]、元[[空手道|空手家]]、元[[ボクサー (スポーツ)|ボクサー]]、元[[キックボクサー]]\n* 1942年 - [[ジョー・バイデン]]、[[政治家]]\n* [[1943年]] - [[浜美枝]]、女優\n* [[1945年]] - [[リック・マンデイ]]、元メジャーリーガー\n* [[1946年]] - [[デュアン・オールマン]]、[[ギタリスト]]（+ [[1971年]]）\n* [[1946年]] - [[猪瀬直樹]]、[[ノンフィクション作家]]、第18代[[東京都知事]]\n* 1946年 - [[徳永二男]]、[[ヴァイオリニスト]]\n* [[1947年]] - [[ジョー・ウォルシュ]]、[[音楽家]]\n* 1947年 - [[上甲秀男]]、プロ野球選手\n* [[1948年]] - [[篠塚建次郎]]、[[ラリー]]ドライバー\n* [[1950年]] - [[渥美マリ]]、元女優、[[歌手]]\n* [[1954年]] - [[島田敏]]、[[声優]]\n* 1954年 - [[和田京平]]、[[審判員|レフェリー]]\n* [[1957年]] - [[ステファン・ベロフ]]、カーレーサー（+ [[1985年]]）\n* 1957年 - [[竹島将]]、作家（+ [[1990年]]）\n* [[1960年]] - [[坪田まり子]]（倉田まり子）、元歌手、女優\n* 1960年 - {{仮リンク|崔一九|ko|최일구}}、放送記者\n* [[1961年]] - [[ピエール・エルメ]]、[[パティシエ]]、[[ショコラティエ]]\n* [[1962年]] - [[あさりよしとお]]、[[漫画家]]\n* 1962年 - {{仮リンク|ラージクマール・ヒラーニ|en|Rajkumar Hirani}}、映画監督\n* [[1963年]] - [[ジム・ワトキンス]]、[[実業家]]、[[2ちゃんねる]](2ch.net)管理人\n* 1963年 - [[鈴木貴久]]、プロ野球選手、コーチ（+ [[2004年]]）\n* 1963年 - [[ミン・ナ]]、女優、声優\n* 1963年 - [[小林千絵]]、歌手、[[タレント]]\n* 1963年 - [[川本和宏]]、元プロ野球選手\n* 1963年 - [[万延海]]、エイズ研究者、人権活動家\n* [[1964年]] - [[アンドレイ・カラシニコフ]]、[[レスリング]]選手\n* 1964年 - [[さくま良子]]、漫画家\n* 1964年 - [[上別府仁資]]、声優\n* 1964年 - [[室塚一也]]、プロ[[車いすマラソン]]ランナー\n* [[1965年]] - [[草尾毅]]、声優\n* 1965年 - [[YOSHIKI]]、ミュージシャン\n* 1965年 - [[光山英和]]、元プロ野球選手\n* [[1966年]] - [[高田佳枝]]（樊建欣）、卓球選手\n* [[1967年]] - [[金谷俊一郎]]、歴史コメンテーター、塾講師\n* [[1969年]] - [[ポール・シェアリング]]、[[脚本家]]\n* 1969年 - [[芙苑晶]]、[[音楽家]]\n* 1969年 - [[sakura (ドラマー)|sakura]]、[[ドラマー]]（元[[L'Arc〜en〜Ciel]]、[[SONS OF ALL PUSSYS]]、[[Lion Heads]]）\n* 1969年 - [[八木さおり]]、女優\n* [[1970年]] - [[原久美子]]、女優、タレント\n* [[1971年]] - [[さくまひでき]]、ミュージシャン\n* [[1972年]] - [[山田広二]]、元プロ野球選手\n* [[1973年]] - [[南雲玲生|dj nagureo（南雲玲生）]]、[[作曲家]]、[[ゲームクリエイター]]\n* 1973年 - [[SU (RIP SLYME)|SU]]、[[MC (ヒップホップ)|MC]]（[[RIP SLYME]]）\n* 1973年 - [[荒木慶大]]、元野球選手、[[プロボクサー]]\n* 1973年 - [[:sr:أماني الحكيم|أماني الحكيم]]、女優、声優\n* [[1974年]] - [[島田大介]]、映像作家、写真家、アートディレクター\n* 1974年 - [[ハチミツ二郎]]、[[お笑いタレント]]（[[東京ダイナマイト]]）、\n* [[1975年]] - [[水野あおい]]、[[ライブアイドル|地下アイドル]]\n* 1975年 - [[桜沢菜々子]]、元[[AV女優]]\n* [[1976年]] - [[米山篤志]]、[[サッカー]]選手\n* [[1977年]] - [[ダニエル・スヴェンソン]]、ミュージシャン\n* [[1978年]] - [[森圭介]]、アナウンサー\n* 1978年 - [[BUCCI]]、MC（[[ET-KING]]）\n<!-- 特筆性は? * [[1979年]] - ドラマチック貞、お笑いタレント（[[スーパースター (お笑いコンビ)|スーパースター]]） -->\n* [[1980年]] - [[小池栄子]]、タレント\n* [[1981年]] - [[西原玲奈]]、[[騎手]]\n* 1981年 - [[川口悠子]]、[[フィギュアスケート]]選手\n* 1981年 - [[藤田大介]]、アナウンサー\n* 1981年 - [[サム・ファルド]]、メジャーリーガー\n* [[1982年]] - [[グレゴール・ウルバス]]、フィギュアスケート選手\n* [[1983年]] - [[稲村尚志]]、[[実業家]]\n* [[1984年]] - [[目黒萌絵]]、[[カーリング]]選手\n* [[1985年]] - [[藤井宏海]]、プロ野球選手\n* 1985年 - [[マリア・ムホルトワ]]、フィギュアスケート選手\n* [[1986年]] - [[塚越広大]]、レーシングドライバー\n* 1986年 - [[堀越耕平]]、漫画家\n* 1986年 - [[アレックス・ゲレーロ]]、プロ野球選手\n* 1986年 - [[カルロス・エドゥアルド・サントス・オリベイラ]]、サッカー選手\n<!-- 特筆性は? * [[1988年]] - 中村一太、ミュージシャン（[[plenty]]） -->\n* [[1989年]] - [[アゴン・メーメティ]]、サッカー選手\n* 1989年 - [[ホームランなみち]]、タレント\n* [[1990年]] - [[大和侑也]]、プロ[[キックボクサー]]\n* [[1991年]] - [[貝森亜理沙]]、[[ピポ☆エンジェルズ]]\n* 1991年 - [[琴恵光充憲]]、大相撲力士\n* [[1991年]] - [[青峰佑樹]]、 俳優\n* [[1992年]] - [[石村舞波]]、元タレント（[[Berryz工房]]）\n* 1992年 - [[松田岳 (俳優)|松田岳]]、俳優\n* 1992年 - [[阿知羅拓馬]]、プロ野球選手\n* 1992年 - [[田村丈]]、プロ野球選手\n* [[1993年]] - [[佐藤すみれ]]、アイドル（[[SKE48]]）\n* 1993年 - [[宮崎香蓮]]、女優\n* 1993年 - [[磯貝初奈]]、アナウンサー\n* [[1994年]] - [[上野紗稀]]、[[サッカー]]選手\n<!-- 特筆性は? * [[1995年]] - マイケル・クリフォード、ミュージシャン（[[ファイヴ・セカンズ・オブ・サマー]]） -->\n<!-- 特筆性は? * [[1996年]] - [[室加奈子]]、アイドル（[[NMB48]]） -->\n* [[1997年]] - [[山崎エリイ]]、声優\n* [[2000年]] - [[コニー・タルボット]]、歌手\n* 2000年 - [[山口まゆ (女優)|山口まゆ]]、女優\n* 生年不明 - [[佐野康之]]、声優\n* 生年不明 - [[川上莉央]]、声優\n* 生年不明 - [[藤村鼓乃美]]、声優\n\n== 忌日 ==\n* [[1419年]]（[[文明 (日本)|文明]]元年[[10月17日 (旧暦)|10月17日]]） - [[一条政房]]、[[室町時代]]の[[公卿]]（* [[1443年]]?）\n* [[1518年]] - [[ピエール・ド・ラ＝リュー]]、[[作曲家]]（* [[1460年]]頃）\n* [[1616年]]（[[元和 (日本)|元和]]2年[[10月12日 (旧暦)|10月12日]]） - [[松前慶広]]、初代[[松前藩|松前藩主]]（* [[1548年]]）\n* [[1708年]]（[[宝永]]5年[[10月9日 (旧暦)|10月9日]]） -  [[藤堂高睦]]、第4代[[津藩|津藩主]]（* [[1667年]]）\n* [[1757年]] - [[キャロライン・オブ・アーンズバック|キャロライン]]、[[ジョージ2世 (イギリス王)|ジョージ2世]]の妃（* [[1683年]]）\n* [[1758年]] - [[ユーハン・ヘルミク・ルーマン]]、[[作曲家]]（* [[1694年]]）\n* [[1764年]] - [[クリスティアン・ゴルトバハ]]、[[数学者]]（* [[1690年]]）\n* [[1856年]] - [[ボーヤイ・ファルカシュ]]、数学者（* [[1775年]]）\n* [[1862年]]（[[文久]]2年[[9月29日 (旧暦)|9月29日]]） - [[松平正和]]、第8代[[大多喜藩|大多喜藩主]]（* [[1823年]]）\n* [[1863年]] - 第8代[[エルギン伯爵]][[ジェイムズ・ブルース (第8代エルギン伯爵)|ジェイムズ・ブルース]]、[[外交官]]、[[植民地]][[官僚]]（* [[1811年]]）\n* [[1871年]]（[[明治]]4年[[10月8日 (旧暦)|10月8日]]） - [[安藤信正]]、第5代[[磐城平藩|磐城平藩主]]、[[江戸幕府]][[老中]]（* [[1820年]]）\n* [[1882年]] - [[ヘンリー・ドレイパー]]、天文学者、[[医師]]（* [[1837年]]）\n* [[1883年]] - [[天璋院]]、[[徳川家定]]の正室（* [[1836年]]）\n* [[1894年]] - [[アントン・ルビンシテイン]]、[[ピアニスト]]、作曲家（* [[1829年]]）\n* [[1910年]] - [[レフ・トルストイ]]、[[小説家]]（* [[1828年]]）\n* [[1919年]] - [[劉師培]]、国学者、教育者、政治家（* [[1884年]]）\n* [[1922年]] - [[沈曾植]]、学者、[[能書家]]（* [[1850年]]）\n* [[1925年]] - [[アレクサンドラ・オブ・デンマーク|アレクサンドラ]]、[[イギリス]]王[[エドワード7世 (イギリス王)|エドワード7世]]の妃（* [[1844年]]）\n* [[1927年]] - [[ヴィルヘルム・ステーンハンマル]]、作曲家（* [[1871年]]）\n* [[1934年]] - [[ウィレム・ド・ジッター]]、[[化学者]]（* [[1872年]]）\n* [[1936年]] - [[ホセ・アントニオ・プリモ・デ・リベラ]]、スペイン[[ファランヘ党]]党首（* [[1903年]]）\n* [[1938年]] - [[松永延造]]、小説家（* [[1895年]]）\n<!--11月30日に移動* [[1939年]] - [[クン・ベーラ]]、ハンガリー・ソビエト共和国の指導者（* [[1886年]]）-->\n* [[1940年]] - [[小熊秀雄]]、[[詩人]]（* [[1901年]]）\n* [[1943年]] - [[川上秋月]]、[[俳優]]、[[噺家]]、[[講釈師]]、[[寄席]][[芸人]]（* [[1873年]]）\n* 1943年 - [[エドワード・ポールトン]]、[[生物学者]]（* [[1856年]]）\n* [[1945年]] - [[本庄繁]]、[[大日本帝国陸軍|日本陸軍]]の[[大将]]、[[関東軍]]司令官（* [[1876年]]）\n* 1945年 - [[フランシス・アストン]]、[[化学者]]（* [[1877年]]）\n* [[1947年]] - [[ヴォルフガング・ボルヒェルト]]、[[小説家]]、[[劇作家]]、[[詩人]]（* [[1920年]]）\n* [[1949年]] - [[若槻禮次郎]]、第25・28代[[内閣総理大臣]]（* [[1866年]]）\n* [[1950年]] - [[フランチェスコ・チレア]]、作曲家（* 1866年）\n* [[1952年]] - [[ベネデット・クローチェ]]、[[思想]]家、[[歴史家]]（* 1866年）\n* [[1958年]] - [[山田孝雄]]、[[日本語学|国語学]]者（* [[1875年]]）\n* [[1960年]] - [[鈴木為次郎]]、[[棋士 (囲碁)|囲碁棋士]]（* [[1883年]]）\n* [[1961年]] - [[小倉正恒]]、元[[大蔵大臣]]、[[実業家]]（* [[1875年]]）\n* [[1965年]] - [[ローレンス・ウェイジャー]]、[[地質学者]]、[[探検家]]（* [[1904年]]）\n* [[1967年]] - [[カシミール・フンク]]、[[生化学|生化学者]]（* [[1884年]]）\n* [[1969年]] - [[中村岳陵]]、[[日本画|日本画家]]（* [[1890年]]）\n* 1969年 - [[アルツール・フリーデンライヒ]]、[[サッカー]]選手（* [[1892年]]）\n* [[1972年]] - [[エンニオ・フライアーノ]]、[[作家]]、[[ジャーナリスト]]（* [[1910年]]）\n* [[1975年]] - [[フランシスコ・フランコ]]、[[軍人]]、[[政治家]]（* 1892年）\n* [[1976年]] - [[トロフィム・ルイセンコ]]、[[農学者]]（* [[1898年]]）\n* 1976年 - [[駒井哲郎]]、[[版画家]]（* [[1920年]]）\n* [[1978年]] - [[ジョルジョ・デ・キリコ]]、[[画家]]（* [[1888年]]）\n* 1978年 - [[オルゴニシュタ・オルガ]]、[[フィギュアスケート]]選手（* [[1901年]]）\n* [[1981年]] - [[小林勇]]、[[編集者]]、[[随筆家]]、[[画家]]（* [[1903年]]）\n* [[1982年]] - [[松田昇 (野球)|松田昇]]、高校野球指導者（* [[1905年]]）\n* [[1984年]] - [[アレクサンデル・モイゼス]]、作曲家（* [[1906年]]）\n* [[1985年]] - [[武智修]]、元[[プロ野球選手]]（* [[1925年]]）\n* [[1986年]] - [[平山嵩]]、[[建築家]]（* [[1903年]]）\n* [[1990年]] - [[ヘルベルト・ケーゲル]]、[[指揮者]]（* 1920年）\n* [[1991年]] - [[山崎正之]]、プロ野球選手（* [[1938年]]）\n* [[1994年]] - [[福田恆存]]、[[評論家]]、[[翻訳家]]、[[劇作家]]（* [[1912年]]）\n* [[1995年]] - [[須田開代子]]、[[ボウリング|プロボウラー]]（* [[1938年]]）\n* 1995年 - [[セルゲイ・グリンコフ]]、[[フィギュアスケート]]選手（* [[1967年]]）\n* [[1998年]] - [[太宰久雄]]、[[俳優]]（* [[1923年]]）\n* [[1999年]] - [[アミントレ・ファンファーニ]]、政治家（* [[1908年]]）\n* [[1999年]] - [[牛久保海平]]、[[サンデンホールディングス|サンデン]]創業者（* [[1905年]]）\n* [[2000年]] - [[三浦真一郎]]、[[プロ野球審判員]]（* [[1946年]]）\n* [[2001年]] - [[フランコ・グッリ]]、[[ヴァイオリニスト]]（* [[1926年]]）\n* 2001年 - [[稲葉誠治]]、アマチュア野球指導者（* [[1917年]]）\n* [[2005年]] - [[村上三島]]、[[書家]]（* [[1921年]]）\n* [[2006年]] - [[斎藤茂太]]、[[作家]]、[[精神科医]]（* [[1916年]]）\n* 2006年 - [[ロバート・アルトマン]]、[[映画監督]]（* [[1925年]]）\n* [[2007年]] - [[三沢郷]]、作曲家（* [[1928年]]）\n* [[2011年]] - [[成田豊]]、[[電通|電通グループ]]の会長（* [[1929年]]）\n* [[2013年]] - [[神楽坂浮子]]、[[うぐいす芸者歌手|芸者歌手]]（* [[1938年]]）\n* [[2014年]] - [[矢野清]]、元プロ野球選手（* [[1940年]]）\n* [[2015年]] - [[北の湖敏満]]、大相撲力士、第55代[[横綱]]、北の湖親方、第9,12代日本相撲協会理事長（* [[1953年]]）\n* [[2016年]] - [[コンスタンディノス・ステファノプロス]]、政治家（* [[1926年]]）\n* 2016年 - [[ウィリアム・トレヴァー]]、小説家（* [[1939年]]）\n* 2016年 - [[島田伸也]]、プロ野球選手（* [[1945年]]）\n\n== 記念日・年中行事 ==\n* [[世界こどもの日]]（{{UN}}）\n*:[[1954年]]の[[国際連合総会|国連総会]]で制定された[[国際デー]]。[[1959年]]に[[児童の権利に関する宣言]]が採択された日。[[1989年]]のこの日には[[児童の権利に関する条約]]の採択も行われている。\n* アフリカ工業化の日（{{UN}}）\n*: [[1989年]]の国連総会で制定された国際デー。\n* [[革命]]記念日（{{MEX}}）\n*: [[1910年]]のこの日に[[メキシコ革命]]が始まったことを記念。\n* [[教師の日|先生の日]]（{{VNM}}）\n*: [[1982年]]制定。教師や先生に感謝する日。\n* [[トランスジェンダー追悼の日]] （{{USA}}）\n*:[[トランスジェンダー]]のリタ・ヘスターが惨殺されたことの追悼に由来。\n* [[えびす講]]（{{JPN}}）\n*: [[えびす|えびす神]]を祭る民間行事。地方によって異なるが[[10月20日]]または[[月遅れ]]で11月20日に行われることが多い。\n* [[毛皮]]の日（{{JPN}}）\n*: [[日本毛皮協会]]が[[1989年]]に制定。「いい(11)ファー(20)」の語呂合せ。\n* [[ピザ]]の日（{{JPN}}）\n*:ピザの原型といわれるピッツァ・マルゲリータの名前の由来となった[[イタリア]]王妃[[マルゲリータ・ディ・サヴォイア＝ジェノヴァ|マルゲリータ]]の誕生日に由来。[[凸版印刷]]が[[1995年]]に制定。\n* 山梨県民の日（{{JPN}} {{flag|山梨県}}）\n*: [[明治]]4年[[11月20日 (旧暦)|旧暦11月20日]]、[[甲府県]]が山梨県に改称されたことに由来し、山梨県が制定。新暦に換算すると12月31日になってしまうため、旧暦の日付を記念日とした。\n<!--*モチモチの木に灯がともる晩([[斎藤隆介]]『[[モチモチの木]]』)\n*:作中では「霜月20日」,すなわちこの日の丑三つ時(午前2時)に主人公とその祖父が住む猟師小屋前のモチモチの木に灯が灯るという現象が描かれている。また,この現象は'''勇気のある1人の男の子しか見ることができないが,祖父・父と二代続けて見た実績がある山の神様の祭典'''とされており,架空であるが'''年中行事の一つ'''とみなす。-->\n\n== フィクションのできごと ==\n{{フィクションの出典明記|section=1|ソートキー=日1120|date=2011年7月}}\n* [[1992年]] - 明訓五人衆などの高校生選手がドラフト指名される。（漫画『[[ドカベン プロ野球編]]』）\n\n=== 誕生日（フィクション） ===\n* 生年不明 - 孔雀舞、漫画『[[遊☆戯☆王]]』に登場するキャラクター<ref>高橋和希 『遊☆戯☆王キャラクターズガイドブック 千年の書』 集英社〈Vジャンプブックス〉、2015年、104頁、ISBN 978-4-08-779722-0。</ref>\n* 生年不明 - 櫻井明音、ゲーム・アニメ『[[ガールフレンド（仮）]]』に登場するキャラクター<ref>ゲーム内のプロフィールより。</ref>\n* 生年不明 - 真中らぁら、ゲーム・アニメ『[[プリパラ]]』及び『[[アイドルタイムプリパラ]]』に登場するキャラクター<ref>{{Twitter status|T_ARTS_PRETTY|533113491649863680}} 2015年8月11日閲覧。</ref><ref>「プリパラ SoLaMi SMILEコーデセット」トモチケ裏面のプロフィールより。</ref><ref>柴崎恵美子『テレビ超ひゃっか プリパラ アイドルずかん』小学館、2016年、6頁、ISBN 978-4-09-750417-7。</ref>\n* 生年不明 - 愛媛なお、ゲーム・アニメ『[[プリパラ]]』に登場するキャラクター<ref>アニメ第71話でらぁらと同じ日とわかる</ref>\n* 生年不明 - 美翔舞、アニメ『[[ふたりはプリキュア Splash Star]]』に登場するキャラクター{{要出典|date=2017年11月19日 (日) 15:54 (UTC)}}\n\n== 出典 ==\n{{脚注ヘルプ}}\n{{Reflist}}\n\n== 関連項目 ==\n{{commonscat|20 November}}\n{{新暦365日|11|19|11|21|[[10月20日]]|[[12月20日]]|[[11月20日 (旧暦)|11月20日]]|1120|11|20}}\n{{1年の月と日}}"}}}]}]}}